Workbook

Sheet INGRESOS
E1: DIARIO DE INGRESOS
A3: FECHA | B3: NOMBRE | C3: APELLIDO | D3: PRODUCTO | E3: CANTIDAD | F3: PRECIO | G3: INGRESO | H3: DESCRIPCION | I3: OBSERVACION | J3: TIPO DE PAGO | K3: MES | L3: AÑO | M3: ORDEN | N3: SOFFI | O3: Columna1
A4: 46023 | B4: ANTERIOR | E4: 1 | F4: 1993.66 | G4: =E4*F4 -> 1993.66 | H4: CANCELACION | I4: SALDO ANTERIOR DE CAJA | J4: EFECTIVO | K4: =UPPER(TEXT(A4,"MMMM")) -> ENERO | L4: =+YEAR(A4) -> 2026
A5: 46023 | B5: SALDO ANTERIOR | E5: 1 | F5: 445.83 | G5: =E5*F5 -> 445.83 | H5: CANCELACION | J5: PICHINCHA | K5: =UPPER(TEXT(A5,"MMMM")) -> ENERO | L5: =+YEAR(A5) -> 2026
A6: 46027 | B6: ERIK | C6: QUITUISACA | D6: LENTES | E6: 1 | F6: 135 | G6: =E6*F6 -> 135 | H6: CANCELACION | J6: EFECTIVO | K6: =UPPER(TEXT(A6,"MMMM")) -> ENERO | L6: =+YEAR(A6) -> 2026
A7: 46027 | B7: KATERINE | C7: AGUILAR | D7: LENTES | E7: 1 | F7: 25 | G7: =E7*F7 -> 25 | H7: CANCELACION | J7: EFECTIVO | K7: =UPPER(TEXT(A7,"MMMM")) -> ENERO | L7: =+YEAR(A7) -> 2026
A8: 46027 | B8: VIVIANA | C8: SANTOS | D8: LENTES | E8: 1 | F8: 40 | G8: =E8*F8 -> 40 | H8: ABONO | J8: EFECTIVO | K8: =UPPER(TEXT(A8,"MMMM")) -> ENERO | L8: =+YEAR(A8) -> 2026
A9: 46028 | B9: ANAHI | C9: CACERES | D9: CERTIFICADO | E9: 1 | F9: 5 | G9: =E9*F9 -> 5 | H9: CANCELACION | J9: EFECTIVO | K9: =UPPER(TEXT(A9,"MMMM")) -> ENERO | L9: =+YEAR(A9) -> 2026
A10: 46028 | B10: ANAHI | C10: PINOS | D10: LENTES | E10: 1 | F10: 20 | G10: =E10*F10 -> 20 | H10: ABONO | J10: EFECTIVO | K10: =UPPER(TEXT(A10,"MMMM")) -> ENERO | L10: =+YEAR(A10) -> 2026
A11: 46028 | B11: BYRON | C11: AYALA | D11: LENTES | E11: 1 | F11: 160 | G11: =E11*F11 -> 160 | H11: CANCELACION | J11: EFECTIVO | K11: =UPPER(TEXT(A11,"MMMM")) -> ENERO | L11: =+YEAR(A11) -> 2026
A12: 46028 | B12: JOSE | C12: LEON | D12: LENTES | E12: 1 | F12: 216.2 | G12: =E12*F12 -> 216.2 | H12: CANCELACION | J12: EFECTIVO | K12: =UPPER(TEXT(A12,"MMMM")) -> ENERO | L12: =+YEAR(A12) -> 2026
A13: 46028 | B13: NANCY | C13: AMENDAÑO | D13: LENTES | E13: 1 | F13: 10 | G13: =E13*F13 -> 10 | H13: ABONO | J13: EFECTIVO | K13: =UPPER(TEXT(A13,"MMMM")) -> ENERO | L13: =+YEAR(A13) -> 2026
A14: 46028 | B14: VIVIANA | C14: SANTOS | D14: LENTES | E14: 1 | F14: 25 | G14: =E14*F14 -> 25 | H14: CANCELACION | J14: EFECTIVO | K14: =UPPER(TEXT(A14,"MMMM")) -> ENERO | L14: =+YEAR(A14) -> 2026
A15: 46029 | B15: CHRISTIAN | C15: AGUILAR | D15: LENTES | E15: 1 | F15: 50 | G15: =E15*F15 -> 50 | H15: ABONO | J15: EFECTIVO | K15: =UPPER(TEXT(A15,"MMMM")) -> ENERO | L15: =+YEAR(A15) -> 2026
A16: 46029 | B16: LUZ | C16: VASQUEZ | D16: LENTES | E16: 1 | F16: 50 | G16: =E16*F16 -> 50 | H16: ABONO | J16: EFECTIVO | K16: =UPPER(TEXT(A16,"MMMM")) -> ENERO | L16: =+YEAR(A16) -> 2026
A17: 46029 | B17: LUZ | C17: VASQUEZ | D17: LENTES | E17: 1 | F17: 125 | G17: =E17*F17 -> 125 | H17: CANCELACION | J17: PICHINCHA | K17: =UPPER(TEXT(A17,"MMMM")) -> ENERO | L17: =+YEAR(A17) -> 2026
A18: 46029 | B18: NANCY | C18: AMENDAÑO | D18: LENTES | E18: 1 | F18: 30 | G18: =E18*F18 -> 30 | H18: CANCELACION | J18: EFECTIVO | K18: =UPPER(TEXT(A18,"MMMM")) -> ENERO | L18: =+YEAR(A18) -> 2026
A19: 46029 | B19: VARILLAS | C19: VARILLAS | D19: LENTES | E19: 1 | F19: 12 | G19: =E19*F19 -> 12 | H19: CANCELACION | I19: CAMBIO VARILLAS | J19: EFECTIVO | K19: =UPPER(TEXT(A19,"MMMM")) -> ENERO | L19: =+YEAR(A19) -> 2026
A20: 46030 | B20: CERTIFICADO | C20: CARTIFICADO | D20: LENTES | E20: 1 | F20: 5 | G20: =E20*F20 -> 5 | H20: CANCELACION | I20: CERTIFICADO VISUAL | J20: EFECTIVO | K20: =UPPER(TEXT(A20,"MMMM")) -> ENERO | L20: =+YEAR(A20) -> 2026
A21: 46030 | B21: CRUCE DE CUENTAS | E21: 1 | F21: 207 | G21: =E21*F21 -> 207 | H21: CANCELACION | I21: CRUCE DE CUENTAS | J21: PICHINCHA | K21: =UPPER(TEXT(A21,"MMMM")) -> ENERO | L21: =+YEAR(A21) -> 2026
A22: 46030 | B22: FREDDY | C22: RODRIGUEZ | D22: LENTES | E22: 1 | F22: 100 | G22: =E22*F22 -> 100 | H22: ABONO | J22: EFECTIVO | K22: =UPPER(TEXT(A22,"MMMM")) -> ENERO | L22: =+YEAR(A22) -> 2026
A23: 46030 | B23: LAURA | C23: MACAS | D23: LENTES | E23: 1 | F23: 110 | G23: =E23*F23 -> 110 | H23: ABONO | I23: RETIRA LENTES | J23: EFECTIVO | K23: =UPPER(TEXT(A23,"MMMM")) -> ENERO | L23: =+YEAR(A23) -> 2026
A24: 46030 | B24: PAULA | C24: CORONEL | E24: 1 | F24: 13.76 | G24: =E24*F24 -> 13.76 | H24: CANCELACION | I24: SERVICION BASICOS | J24: PICHINCHA | K24: =UPPER(TEXT(A24,"MMMM")) -> ENERO | L24: =+YEAR(A24) -> 2026
A25: 46031 | B25: ANAHI | C25: PINOS | D25: LENTES | E25: 1 | F25: 155 | G25: =E25*F25 -> 155 | H25: CANCELACION | J25: EFECTIVO | K25: =UPPER(TEXT(A25,"MMMM")) -> ENERO | L25: =+YEAR(A25) -> 2026
A26: 46031 | B26: CERTIFICADO | C26: CERTIFICADO | D26: CERTIFICADO | E26: 1 | F26: 5 | G26: =E26*F26 -> 5 | H26: CANCELACION | J26: EFECTIVO | K26: =UPPER(TEXT(A26,"MMMM")) -> ENERO | L26: =+YEAR(A26) -> 2026
A27: 46031 | B27: DAIRA | C27: VILLOTA | D27: LENTES | E27: 1 | F27: 20 | G27: =E27*F27 -> 20 | H27: ABONO | J27: EFECTIVO | K27: =UPPER(TEXT(A27,"MMMM")) -> ENERO | L27: =+YEAR(A27) -> 2026
A28: 46031 | B28: DAYRA | C28: VILLOTA | D28: LENTES | E28: 1 | F28: 80 | G28: =E28*F28 -> 80 | H28: CANCELACION | J28: DE UNA | K28: =UPPER(TEXT(A28,"MMMM")) -> ENERO | L28: =+YEAR(A28) -> 2026
A29: 46031 | B29: JUAN | C29: PADILLA | D29: LENTES | E29: 1 | F29: 79 | G29: =E29*F29 -> 79 | H29: CANCELACION | I29: CREDITO | J29: EFECTIVO | K29: =UPPER(TEXT(A29,"MMMM")) -> ENERO | L29: =+YEAR(A29) -> 2026
A30: 46031 | B30: SEGUNDO | C30: PARDO | D30: LENTES | E30: 1 | F30: 140 | G30: =E30*F30 -> 140 | H30: ABONO | J30: EFECTIVO | K30: =UPPER(TEXT(A30,"MMMM")) -> ENERO | L30: =+YEAR(A30) -> 2026
A31: 46031 | B31: WILSON | C31: CASTRO | D31: LENTES | E31: 1 | F31: 20 | G31: =E31*F31 -> 20 | H31: ABONO | J31: EFECTIVO | K31: =UPPER(TEXT(A31,"MMMM")) -> ENERO | L31: =+YEAR(A31) -> 2026
A32: 46032 | B32: LAURA | C32: RUMIPULLA | D32: LENTES | E32: 1 | F32: 20 | G32: =E32*F32 -> 20 | H32: ABONO | J32: EFECTIVO | K32: =UPPER(TEXT(A32,"MMMM")) -> ENERO | L32: =+YEAR(A32) -> 2026
A33: 46032 | B33: MANUEL | C33: MELGAR | D33: LENTES | E33: 1 | F33: 20 | G33: =E33*F33 -> 20 | H33: ABONO | J33: EFECTIVO | K33: =UPPER(TEXT(A33,"MMMM")) -> ENERO | L33: =+YEAR(A33) -> 2026
A34: 46034 | B34: CERTIFICADO | C34: CERTIFICADO | D34: CERTIFICADO | E34: 1 | F34: 5 | G34: =E34*F34 -> 5 | H34: CANCELACION | J34: EFECTIVO | K34: =UPPER(TEXT(A34,"MMMM")) -> ENERO | L34: =+YEAR(A34) -> 2026
A35: 46035 | B35: CARMEN | C35: ALVARADO | D35: LENTES | E35: 1 | F35: 60 | G35: =E35*F35 -> 60 | H35: ABONO | J35: EFECTIVO | K35: =UPPER(TEXT(A35,"MMMM")) -> ENERO | L35: =+YEAR(A35) -> 2026
A36: 46035 | B36: ILDA | C36: PAUCAR | D36: LENTES | E36: 1 | F36: 60 | G36: =E36*F36 -> 60 | H36: ABONO | J36: EFECTIVO | K36: =UPPER(TEXT(A36,"MMMM")) -> ENERO | L36: =+YEAR(A36) -> 2026
A37: 46035 | B37: JESSICA | C37: PATIÑO | D37: LENTES | E37: 1 | F37: 100 | G37: =E37*F37 -> 100 | H37: ABONO | J37: EFECTIVO | K37: =UPPER(TEXT(A37,"MMMM")) -> ENERO | L37: =+YEAR(A37) -> 2026
A38: 46035 | B38: PIEDAD | C38: BARRERA | D38: LENTES | E38: 1 | F38: 70 | G38: =E38*F38 -> 70 | H38: ABONO | J38: EFECTIVO | K38: =UPPER(TEXT(A38,"MMMM")) -> ENERO | L38: =+YEAR(A38) -> 2026
A39: 46035 | B39: TORNILLO | C39: TORNILLO | D39: ACCESORIOS | E39: 1 | F39: 1 | G39: =E39*F39 -> 1 | H39: CANCELACION | J39: EFECTIVO | K39: =UPPER(TEXT(A39,"MMMM")) -> ENERO | L39: =+YEAR(A39) -> 2026
A40: 46036 | B40: ACCESORIOS | C40: ACCESORIOS | D40: ACCESORIOS | E40: 1 | F40: 8.5 | G40: =E40*F40 -> 8.5 | H40: CANCELACION | I40: ACCESORIOS | J40: EFECTIVO | K40: =UPPER(TEXT(A40,"MMMM")) -> ENERO | L40: =+YEAR(A40) -> 2026
A41: 46036 | B41: CARMEN | C41: ALVARADO | D41: LENTES | E41: 1 | F41: 70 | G41: =E41*F41 -> 70 | H41: CANCELACION | I41: LENTES + PLAQUETAS | J41: EFECTIVO | K41: =UPPER(TEXT(A41,"MMMM")) -> ENERO | L41: =+YEAR(A41) -> 2026
A42: 46036 | B42: ERNESTO | C42: RAMOS | D42: LENTES | E42: 1 | F42: 60 | G42: =E42*F42 -> 60 | H42: ABONO | J42: EFECTIVO | K42: =UPPER(TEXT(A42,"MMMM")) -> ENERO | L42: =+YEAR(A42) -> 2026
A43: 46036 | B43: JESSICA | C43: PATIÑO | D43: LENTES | E43: 1 | F43: 90 | G43: =E43*F43 -> 90 | H43: CANCELACION | J43: EFECTIVO | K43: =UPPER(TEXT(A43,"MMMM")) -> ENERO | L43: =+YEAR(A43) -> 2026
A44: 46036 | B44: LAURA | C44: RUMIPULLA | D44: LENTES | E44: 1 | F44: 120 | G44: =E44*F44 -> 120 | H44: CANCELACION | J44: EFECTIVO | K44: =UPPER(TEXT(A44,"MMMM")) -> ENERO | L44: =+YEAR(A44) -> 2026
A45: 46036 | B45: MANUEL | C45: MELGAR | D45: LENTES | E45: 1 | F45: 15 | G45: =E45*F45 -> 15 | H45: CANCELACION | J45: EFECTIVO | K45: =UPPER(TEXT(A45,"MMMM")) -> ENERO | L45: =+YEAR(A45) -> 2026
A46: 46036 | B46: PABLO | C46: DOMINGUEZ | D46: LENTES | E46: 1 | F46: 125 | G46: =E46*F46 -> 125 | H46: CANCELACION | J46: EFECTIVO | K46: =UPPER(TEXT(A46,"MMMM")) -> ENERO | L46: =+YEAR(A46) -> 2026
A47: 46036 | B47: SEGUNDO | C47: PARDO | D47: LENTES | E47: 1 | F47: 40 | G47: =E47*F47 -> 40 | H47: CANCELACION | J47: EFECTIVO | K47: =UPPER(TEXT(A47,"MMMM")) -> ENERO | L47: =+YEAR(A47) -> 2026
A48: 46037 | B48: ACCESORIOS | C48: ACCESORIOS | D48: ACCESORIOS | E48: 1 | F48: 12 | G48: =E48*F48 -> 12 | H48: CANCELACION | I48: VARILLAS | J48: EFECTIVO | K48: =UPPER(TEXT(A48,"MMMM")) -> ENERO | L48: =+YEAR(A48) -> 2026
A49: 46037 | B49: ANA | C49: CHOCHO | D49: LENTES | E49: 1 | F49: 40 | G49: =E49*F49 -> 40 | H49: ABONO | J49: EFECTIVO | K49: =UPPER(TEXT(A49,"MMMM")) -> ENERO | L49: =+YEAR(A49) -> 2026
A50: 46037 | B50: ANTONIO | C50: VARELA | D50: LENTES | E50: 1 | F50: 40 | G50: =E50*F50 -> 40 | H50: ABONO | J50: EFECTIVO | K50: =UPPER(TEXT(A50,"MMMM")) -> ENERO | L50: =+YEAR(A50) -> 2026
A51: 46037 | B51: DAYRA | C51: VILLOTA | D51: LENTES | E51: 1 | F51: 190 | G51: =E51*F51 -> 190 | H51: CANCELACION | J51: DE UNA | K51: =UPPER(TEXT(A51,"MMMM")) -> ENERO | L51: =+YEAR(A51) -> 2026
A52: 46037 | B52: VICTOR | C52: AVILES | D52: LENTES | E52: 1 | F52: 40 | G52: =E52*F52 -> 40 | H52: ABONO | J52: EFECTIVO | K52: =UPPER(TEXT(A52,"MMMM")) -> ENERO | L52: =+YEAR(A52) -> 2026
A53: 46041 | B53: ACCESORIOS | C53: ACCESORIOS | D53: ACCESORIOS | E53: 1 | F53: 2 | G53: =E53*F53 -> 2 | H53: CANCELACION | I53: ESTUCHE Y NAILON | J53: EFECTIVO | K53: =UPPER(TEXT(A53,"MMMM")) -> ENERO | L53: =+YEAR(A53) -> 2026
A54: 46041 | B54: JOSUE | C54: MENDEZ | D54: LENTES | E54: 1 | F54: 40 | G54: =E54*F54 -> 40 | H54: ABONO | I54: CREDITO | J54: EFECTIVO | K54: =UPPER(TEXT(A54,"MMMM")) -> ENERO | L54: =+YEAR(A54) -> 2026
A55: 46041 | B55: PIEDAD | C55: BARRERA | D55: LENTES | E55: 1 | F55: 200 | G55: =E55*F55 -> 200 | H55: CANCELACION | J55: EFECTIVO | K55: =UPPER(TEXT(A55,"MMMM")) -> ENERO | L55: =+YEAR(A55) -> 2026
A56: 46041 | B56: FABIAN | C56: PAUCAR | D56: LENTES | E56: 1 | F56: 115 | G56: =E56*F56 -> 115 | H56: CANCELACION | J56: EFECTIVO | K56: =UPPER(TEXT(A56,"MMMM")) -> ENERO | L56: =+YEAR(A56) -> 2026
A57: 46042 | B57: ERNESTO | C57: RAMOS | D57: LENTES | E57: 1 | F57: 200 | G57: =E57*F57 -> 200 | H57: CANCELACION | J57: EFECTIVO | K57: =UPPER(TEXT(A57,"MMMM")) -> ENERO | L57: =+YEAR(A57) -> 2026
A58: 46043 | B58: ACCESORIOS | C58: ACCESORIOS | D58: ACCESORIOS | E58: 1 | F58: 0.5 | G58: =E58*F58 -> 0.5 | H58: CANCELACION | J58: EFECTIVO | K58: =UPPER(TEXT(A58,"MMMM")) -> ENERO | L58: =+YEAR(A58) -> 2026
A59: 46043 | B59: ALEX | C59: LOJA | D59: LENTES | E59: 1 | F59: 60 | G59: =E59*F59 -> 60 | H59: ABONO | J59: EFECTIVO | K59: =UPPER(TEXT(A59,"MMMM")) -> ENERO | L59: =+YEAR(A59) -> 2026
A60: 46043 | B60: ANA | C60: CHOCHO | D60: LENTES | E60: 1 | F60: 125 | G60: =E60*F60 -> 125 | H60: CANCELACION | J60: EFECTIVO | K60: =UPPER(TEXT(A60,"MMMM")) -> ENERO | L60: =+YEAR(A60) -> 2026
A61: 46043 | B61: ANTONIO | C61: VARELA | D61: LENTES | E61: 1 | F61: 270 | G61: =E61*F61 -> 270 | H61: CANCELACION | J61: EFECTIVO | K61: =UPPER(TEXT(A61,"MMMM")) -> ENERO | L61: =+YEAR(A61) -> 2026
A62: 46043 | B62: KATHERINE | C62: MURILLO | D62: LENTES | E62: 1 | F62: 40 | G62: =E62*F62 -> 40 | H62: ABONO | J62: EFECTIVO | K62: =UPPER(TEXT(A62,"MMMM")) -> ENERO | L62: =+YEAR(A62) -> 2026
A63: 46043 | B63: LIQUIDO DE L/C | C63: LIQUIDO | D63: ACCESORIOS | E63: 1 | F63: 7 | G63: =E63*F63 -> 7 | H63: CANCELACION | I63: LIQUIDO DE L/C | J63: EFECTIVO | K63: =UPPER(TEXT(A63,"MMMM")) -> ENERO | L63: =+YEAR(A63) -> 2026
A64: 46044 | B64: ACCESORIOS | C64: ACCESORIOS | D64: ACCESORIOS | E64: 1 | F64: 4 | G64: =E64*F64 -> 4 | H64: CANCELACION | I64: ARREGLO ARMAZON | J64: EFECTIVO | K64: =UPPER(TEXT(A64,"MMMM")) -> ENERO | L64: =+YEAR(A64) -> 2026
A65: 46044 | B65: ALEX | C65: LOJA | D65: LENTES | E65: 1 | F65: 50 | G65: =E65*F65 -> 50 | H65: CANCELACION | J65: EFECTIVO | K65: =UPPER(TEXT(A65,"MMMM")) -> ENERO | L65: =+YEAR(A65) -> 2026
A66: 46044 | B66: KATERINE | C66: MURILLO | D66: LENTES | E66: 1 | F66: 90 | G66: =E66*F66 -> 90 | H66: CANCELACION | J66: EFECTIVO | K66: =UPPER(TEXT(A66,"MMMM")) -> ENERO | L66: =+YEAR(A66) -> 2026
A67: 46045 | B67: ENMA | C67: DOMINGUEZ | D67: LENTES | E67: 1 | F67: 50 | G67: =E67*F67 -> 50 | H67: ABONO | J67: JEP DANNA | K67: =UPPER(TEXT(A67,"MMMM")) -> ENERO | L67: =+YEAR(A67) -> 2026
A68: 46045 | B68: NICOLAS | C68: ANDRADE | D68: LENTES | E68: 1 | F68: 50 | G68: =E68*F68 -> 50 | H68: ABONO | J68: EFECTIVO | K68: =UPPER(TEXT(A68,"MMMM")) -> ENERO | L68: =+YEAR(A68) -> 2026
A69: 46045 | B69: RAUL | C69: CHALCO | D69: LENTES | E69: 1 | F69: 50 | G69: =E69*F69 -> 50 | H69: ABONO | J69: EFECTIVO | K69: =UPPER(TEXT(A69,"MMMM")) -> ENERO | L69: =+YEAR(A69) -> 2026
A70: 46046 | B70: XAVIER | C70: VASQUEZ | D70: LENTES | E70: 1 | F70: 40 | G70: =E70*F70 -> 40 | H70: ABONO | I70: ABONO L/C | J70: EFECTIVO | K70: =UPPER(TEXT(A70,"MMMM")) -> ENERO | L70: =+YEAR(A70) -> 2026 | M70: SALDO 30
A71: 46049 | B71: EDGAR | C71: ZUMBA | D71: CERTIFICADO | E71: 1 | F71: 5 | G71: =E71*F71 -> 5 | H71: CANCELACION | J71: EFECTIVO | K71: =UPPER(TEXT(A71,"MMMM")) -> ENERO | L71: =+YEAR(A71) -> 2026
A72: 46049 | B72: FRANCISCO | C72: ALVAREZ | D72: CERTIFICADO | E72: 1 | F72: 5 | G72: =E72*F72 -> 5 | H72: CANCELACION | J72: EFECTIVO | K72: =UPPER(TEXT(A72,"MMMM")) -> ENERO | L72: =+YEAR(A72) -> 2026
A73: 46049 | B73: JULIO | C73: ARIZAGA | D73: LENTES | E73: 1 | F73: 45 | G73: =E73*F73 -> 45 | H73: CANCELACION | J73: EFECTIVO | K73: =UPPER(TEXT(A73,"MMMM")) -> ENERO | L73: =+YEAR(A73) -> 2026
A74: 46050 | B74: DARWIN | C74: PUCHA | D74: CERTIFICADO | E74: 1 | F74: 5 | G74: =E74*F74 -> 5 | H74: CANCELACION | J74: EFECTIVO | K74: =UPPER(TEXT(A74,"MMMM")) -> ENERO | L74: =+YEAR(A74) -> 2026
A75: 46050 | B75: ELISMAR | C75: CARMONA | D75: LENTES | E75: 1 | F75: 20 | G75: =E75*F75 -> 20 | H75: CANCELACION | J75: EFECTIVO | K75: =UPPER(TEXT(A75,"MMMM")) -> ENERO | L75: =+YEAR(A75) -> 2026
A76: 46050 | B76: JONAS | C76: TRELLES | D76: CERTIFICADO | E76: 1 | F76: 5 | G76: =E76*F76 -> 5 | H76: CANCELACION | J76: EFECTIVO | K76: =UPPER(TEXT(A76,"MMMM")) -> ENERO | L76: =+YEAR(A76) -> 2026
B77: ELISMAR | C77: CARMONA | D77: LENTES | E77: 1 | F77: 40 | G77: =E77*F77 -> 40 | H77: ABONO | J77: EFECTIVO | K77: =UPPER(TEXT(A127,"MMMM")) -> ENERO | L77: =+YEAR(A127) -> 1900
A78: 46050 | B78: RAUL | C78: CHALCO | D78: LENTES | E78: 1 | F78: 60 | G78: =E78*F78 -> 60 | H78: CANCELACION | J78: EFECTIVO | K78: =UPPER(TEXT(A78,"MMMM")) -> ENERO | L78: =+YEAR(A78) -> 2026
A79: 46050 | B79: SEÑOR PREFECTURA | D79: LENTES | E79: 1 | F79: 10 | G79: =E79*F79 -> 10 | H79: CANCELACION | I79: SALDO DE ARMAZON | J79: EFECTIVO | K79: =UPPER(TEXT(A79,"MMMM")) -> ENERO | L79: =+YEAR(A79) -> 2026
A80: 46053 | B80: DANIEL | C80: MENDOZA | D80: ACCESORIOS | E80: 1 | F80: 1 | G80: =E80*F80 -> 1 | H80: FUNDAS VENDIDAS | J80: EFECTIVO | K80: =UPPER(TEXT(A80,"MMMM")) -> ENERO | L80: =+YEAR(A80) -> 2026
A81: 46053 | B81: DARWIN | C81: PUCHA | D81: LENTES | E81: 1 | F81: 25 | G81: =E81*F81 -> 25 | H81: ABONO | J81: EFECTIVO | K81: =UPPER(TEXT(A81,"MMMM")) -> ENERO | L81: =+YEAR(A81) -> 2026
A82: 46053 | B82: JULIO | C82: CRIOLLO | D82: CERTIFICADO | E82: 1 | F82: 5 | G82: =E82*F82 -> 5 | H82: CANCELACION | J82: EFECTIVO | K82: =UPPER(TEXT(A82,"MMMM")) -> ENERO | L82: =+YEAR(A82) -> 2026
A83: 46053 | B83: LINDA | C83: VEGA | D83: LENTES | E83: 1 | F83: 170 | G83: =E83*F83 -> 170 | H83: CANCELACION | J83: EFECTIVO | K83: =UPPER(TEXT(A83,"MMMM")) -> ENERO | L83: =+YEAR(A83) -> 2026
A84: 46055 | B84: DEPOSITO | C84: BANCO BARRIO | D84: LENTES | E84: 1 | F84: 300 | G84: =E84*F84 -> 300 | H84: DEPOSITO | J84: PICHINCHA | K84: =UPPER(TEXT(A84,"MMMM")) -> FEBRERO | L84: =+YEAR(A84) -> 2026
A85: 46055 | B85: CRUCE DE CUENTAS | C85: CRUCE ENTRE CUENTAS | D85: LENTES | E85: 1 | F85: 30 | G85: =E85*F85 -> 30 | H85: DEPOSITO | J85: PICHINCHA | K85: =UPPER(TEXT(A85,"MMMM")) -> FEBRERO | L85: =+YEAR(A85) -> 2026
A86: 46056 | B86: DIEGO | C86: CEDILLO | D86: CERTIFICADO | E86: 1 | F86: 5 | G86: =E86*F86 -> 5 | H86: CANCELACION | J86: EFECTIVO | K86: =UPPER(TEXT(A86,"MMMM")) -> FEBRERO | L86: =+YEAR(A86) -> 2026
A87: 46056 | B87: HESS | C87: VASQUEZ | D87: CERTIFICADO | E87: 1 | F87: 5 | G87: =E87*F87 -> 5 | H87: CANCELACION | J87: EFECTIVO | K87: =UPPER(TEXT(A87,"MMMM")) -> FEBRERO | L87: =+YEAR(A87) -> 2026
A88: 46056 | B88: faBIAN | C88: DOMINGUEZ | D88: LENTES | E88: 1 | F88: 100 | G88: =E88*F88 -> 100 | H88: CANCELACION | J88: JEP DANNA | K88: =UPPER(TEXT(A88,"MMMM")) -> FEBRERO | L88: =+YEAR(A88) -> 2026
A89: 46057 | B89: FABIAN | C89: MARIN | D89: LENTES | E89: 1 | F89: 225 | G89: =E89*F89 -> 225 | H89: CANCELACION | J89: EFECTIVO | K89: =UPPER(TEXT(A89,"MMMM")) -> FEBRERO | L89: =+YEAR(A89) -> 2026
A90: 46057 | B90: PAUL | C90: SUÑA | D90: LENTES | E90: 1 | F90: 40 | G90: =E90*F90 -> 40 | H90: CANCELACION | J90: EFECTIVO | K90: =UPPER(TEXT(A90,"MMMM")) -> FEBRERO | L90: =+YEAR(A90) -> 2026
A91: 46057 | B91: GAD PROVINCIAL | C91: EMPLEADOS | D91: LENTES | E91: 1 | F91: 57.5 | G91: =E91*F91 -> 57.5 | H91: ABONOS | J91: JEP DANNA | K91: =UPPER(TEXT(A91,"MMMM")) -> FEBRERO | L91: =+YEAR(A91) -> 2026
... A108: 46064 | B108: WILLIAM | C108: SARI | D108: LENTES | E108: 1 | F108: 70 | G108: =E108*F108 -> 70 | H108: CANCELACION | J108: EFECTIVO | K108: =UPPER(TEXT(A108,"MMMM")) -> FEBRERO | L108: =+YEAR(A108) -> 2026
A109: 46064 | B109: ACCESORIOS | C109: ACCESORIOS | D109: ACCESORIOS | E109: 1 | F109: 5 | G109: =E109*F109 -> 5 | H109: CANCELACION | I109: PLAQUETAS | J109: EFECTIVO | K109: =UPPER(TEXT(A109,"MMMM")) -> FEBRERO | L109: =+YEAR(A109) -> 2026
A110: 46064 | B110: PATRICIO | C110: QUITO | D110: LENTES | E110: 1 | F110: 200 | G110: =E110*F110 -> 200 | H110: CANCELACION | J110: EFECTIVO | K110: =UPPER(TEXT(A110,"MMMM")) -> FEBRERO | L110: =+YEAR(A110) -> 2026
A111: 46065 | B111: PAGOS SERVICIOS ( PAULA CORONEL) | C111: PAGO SERVICIOS | D111: LENTES | E111: 1 | F111: 14.43 | G111: =E111*F111 -> 14.43 | H111: CANCELACION | J111: PICHINCHA | K111: =UPPER(TEXT(A111,"MMMM")) -> FEBRERO | L111: =+YEAR(A111) -> 2026
A112: 46066 | B112: EDUARDO | C112: CANDO | D112: LENTES | E112: 1 | F112: 200 | G112: =E112*F112 -> 200 | H112: ABONO | J112: DE UNA | K112: =UPPER(TEXT(A112,"MMMM")) -> FEBRERO | L112: =+YEAR(A112) -> 2026
A113: 46067 | B113: PEDRO | C113: CHALCO | D113: LENTES | E113: 1 | F113: 145 | G113: =E113*F113 -> 145 | H113: ABONO | J113: EFECTIVO | K113: =UPPER(TEXT(A113,"MMMM")) -> FEBRERO | L113: =+YEAR(A113) -> 2026
A114: 46067 | B114: DIEGO | C114: ZARUMEÑO | D114: LENTES | E114: 1 | F114: 55 | G114: =E114*F114 -> 55 | H114: CANCELACION | J114: EFECTIVO | K114: =UPPER(TEXT(A114,"MMMM")) -> FEBRERO | L114: =+YEAR(A114) -> 2026
A115: 46067 | B115: ADRIAN | C115: QUITO | D115: LENTES | E115: 1 | F115: 70 | G115: =E115*F115 -> 70 | H115: CANCELACION | J115: EFECTIVO | K115: =UPPER(TEXT(A115,"MMMM")) -> FEBRERO | L115: =+YEAR(A115) -> 2026
A116: 46067 | B116: ARIANA | C116: BOJORQUE | D116: LENTES | E116: 1 | F116: 95 | G116: =E116*F116 -> 95 | H116: CANCELACION | I116: LENTES DE CONTACTO | J116: EFECTIVO | K116: =UPPER(TEXT(A116,"MMMM")) -> FEBRERO | L116: =+YEAR(A116) -> 2026
A117: 46071 | B117: MATEO | C117: TENEZACA | D117: LENTES | E117: 1 | F117: 40 | G117: =E117*F117 -> 40 | H117: ABONO | J117: EFECTIVO | K117: =UPPER(TEXT(A117,"MMMM")) -> FEBRERO | L117: =+YEAR(A117) -> 2026
...

Sheet EGRESOS
G1: DIARIO DE EGRESOS
A3: FECHA | B3: CUENTA | C3: DISTRIBUIDOR | D3: CANTIDAD | E3: PRECIO | F3: EGRESO | G3: DETALLE ADICIONAL | H3: NO. DOCUMENTO | I3: MES | J3: AÑO | K3: TIPO DE PAGO | L3: Columna1
A4: 46027 | B4: COMIDA | C4: OTROS | D4: 1 | E4: 7.3 | F4: =Tabla8[[#This Row],[CANTIDAD]]*Tabla8[[#This Row],[PRECIO]] -> 7.3 | G4: FRUTAS | I4: =UPPER(TEXT(A4,"MMMM")) -> ENERO | J4: =+YEAR(A4) -> 2026 | K4: EFECTIVO
A5: 46027 | B5: DANNA | C5: PERSONAL | D5: 1 | E5: 22 | F5: =Tabla8[[#This Row],[CANTIDAD]]*Tabla8[[#This Row],[PRECIO]] -> 22 | G5: ADELANTO DANNA | I5: =UPPER(TEXT(A5,"MMMM")) -> ENERO | J5: =+YEAR(A5) -> 2026 | K5: EFECTIVO
A6: 46027 | B6: BRYAM | C6: PERSONAL | D6: 1 | E6: 15 | F6: =Tabla8[[#This Row],[CANTIDAD]]*Tabla8[[#This Row],[PRECIO]] -> 15 | G6: REGALO AMIGO SECRETO | I6: =UPPER(TEXT(A6,"MMMM")) -> ENERO | J6: =+YEAR(A6) -> 2026 | K6: EFECTIVO
A7: 46027 | B7: DEPOSITO | C7: AHORRO META | D7: 1 | E7: 5 | F7: =Tabla8[[#This Row],[CANTIDAD]]*Tabla8[[#This Row],[PRECIO]] -> 5 | G7: AHORRO META PRODUBANCO | I7: =UPPER(TEXT(A7,"MMMM")) -> ENERO | J7: =+YEAR(A7) -> 2026 | K7: PRODUBANCO
A8: 46027 | B8: DEPOSITO | C8: AHORRO META | D8: 1 | E8: 5 | F8: =Tabla8[[#This Row],[CANTIDAD]]*Tabla8[[#This Row],[PRECIO]] -> 5 | G8: AHORRO META PRODUBANCO | I8: =UPPER(TEXT(A8,"MMMM")) -> ENERO | J8: =+YEAR(A8) -> 2026 | K8: PRODUBANCO
A9: 46027 | B9: DANNA | C9: PERSONAL | D9: 1 | E9: 20 | F9: =Tabla8[[#This Row],[CANTIDAD]]*Tabla8[[#This Row],[PRECIO]] -> 20 | G9: ADELANTO | I9: =UPPER(TEXT(A9,"MMMM")) -> ENERO | J9: =+YEAR(A9) -> 2026 | K9: PICHINCHA
A10: 46027 | B10: COMPRAS | C10: IMPORTLENTS | D10: 1 | E10: 233.47 | F10: =Tabla8[[#This Row],[CANTIDAD]]*Tabla8[[#This Row],[PRECIO]] -> 233.47 | G10: PAGO FACTURAS | I10: =UPPER(TEXT(A10,"MMMM")) -> ENERO | J10: =+YEAR(A10) -> 2026 | K10: PICHINCHA
A11: 46027 | B11: COMPRAS | C11: DELBAK | D11: 1 | E11: 10.93 | F11: =Tabla8[[#This Row],[CANTIDAD]]*Tabla8[[#This Row],[PRECIO]] -> 10.93 | G11: PAGO FACTURAS | I11: =UPPER(TEXT(A11,"MMMM")) -> ENERO | J11: =+YEAR(A11) -> 2026 | K11: PICHINCHA
A12: 46027 | B12: COMPRAS | C12: PROVISION CUENCA | D12: 1 | E12: 68 | F12: =Tabla8[[#This Row],[CANTIDAD]]*Tabla8[[#This Row],[PRECIO]] -> 68 | G12: ARMAZONES | I12: =UPPER(TEXT(A12,"MMMM")) -> ENERO | J12: =+YEAR(A12) -> 2026 | K12: PICHINCHA
A13: 46027 | B13: COMPRAS | C13: TECNILENTS | D13: 1 | E13: 55.61 | F13: =Tabla8[[#This Row],[CANTIDAD]]*Tabla8[[#This Row],[PRECIO]] -> 55.61 | G13: PAGO FACTURAS | I13: =UPPER(TEXT(A13,"MMMM")) -> ENERO | J13: =+YEAR(A13) -> 2026 | K13: PICHINCHA
A14: 46028 | B14: COMPRAS | C14: OTROS | D14: 1 | E14: 73 | F14: =Tabla8[[#This Row],[CANTIDAD]]*Tabla8[[#This Row],[PRECIO]] -> 73 | G14: COMPRAS CORAL CENTRO | I14: =UPPER(TEXT(A14,"MMMM")) -> ENERO | J14: =+YEAR(A14) -> 2026 | K14: EFECTIVO
A15: 46028 | B15: COMPRAS | C15: OTROS | D15: 1 | E15: 3 | F15: =Tabla8[[#This Row],[CANTIDAD]]*Tabla8[[#This Row],[PRECIO]] -> 3 | G15: PAN | I15: =UPPER(TEXT(A15,"MMMM")) -> ENERO | J15: =+YEAR(A15) -> 2026 | K15: EFECTIVO
... A109: 46058 | B109: COMIDA | C109: PERSONAL | D109: 1 | E109: 13.75 | F109: =Tabla8[[#This Row],[CANTIDAD]]*Tabla8[[#This Row],[PRECIO]] -> 13.75 | G109: ALMUERZOS | I109: =UPPER(TEXT(A109,"MMMM")) -> FEBRERO | J109: =+YEAR(A109) -> 2026 | K109: EFECTIVO
A110: 46058 | B110: COMIDA | C110: PERSONAL | D110: 1 | E110: 7.5 | F110: =Tabla8[[#This Row],[CANTIDAD]]*Tabla8[[#This Row],[PRECIO]] -> 7.5 | G110: COMIDA DANNA Y BRYAM | I110: =UPPER(TEXT(A110,"MMMM")) -> FEBRERO | J110: =+YEAR(A110) -> 2026 | K110: PICHINCHA | L110: DE UNA
A111: 46059 | B111: COMPRAS | C111: PROVISION CUENCA | D111: 1 | E111: 27 | F111: =Tabla8[[#This Row],[CANTIDAD]]*Tabla8[[#This Row],[PRECIO]] -> 27 | G111: COMPRAS OPTICA | I111: =UPPER(TEXT(A111,"MMMM")) -> FEBRERO | J111: =+YEAR(A111) -> 2026 | K111: PICHINCHA
A112: 46059 | B112: BRYAM | C112: PERSONAL | D112: 1 | E112: 5 | F112: =Tabla8[[#This Row],[CANTIDAD]]*Tabla8[[#This Row],[PRECIO]] -> 5 | G112: TABLA ZHINDON BRYAM | I112: =UPPER(TEXT(A112,"MMMM")) -> FEBRERO | J112: =+YEAR(A112) -> 2026 | K112: PICHINCHA
A113: 46059 | B113: DEPOSITO | C113: PAGO IESS | D113: 1 | E113: 188.94 | F113: =Tabla8[[#This Row],[CANTIDAD]]*Tabla8[[#This Row],[PRECIO]] -> 188.94 | G113: IESS DANNA Y BRYAM | I113: =UPPER(TEXT(A113,"MMMM")) -> FEBRERO | J113: =+YEAR(A113) -> 2026 | K113: PRODUBANCO
A114: 46059 | B114: COMIDA | C114: PERSONAL | D114: 1 | E114: 23.84 | F114: =Tabla8[[#This Row],[CANTIDAD]]*Tabla8[[#This Row],[PRECIO]] -> 23.84 | G114: COMIDA DANNA Y BRYAM | I114: =UPPER(TEXT(A114,"MMMM")) -> FEBRERO | J114: =+YEAR(A114) -> 2026 | K114: PRODUBANCO
A115: 46059 | B115: DEPOSITO | C115: PAGO IESS COMISION | D115: 1 | E115: 0.31 | F115: =Tabla8[[#This Row],[CANTIDAD]]*Tabla8[[#This Row],[PRECIO]] -> 0.31 | G115: IESS DANNA Y BYRAM COMICION | I115: =UPPER(TEXT(A115,"MMMM")) -> FEBRERO | J115: =+YEAR(A115) -> 2026 | K115: PRODUBANCO
A116: 46059 | B116: COMPRAS | C116: OPTICA | D116: 1 | E116: 27 | F116: =Tabla8[[#This Row],[CANTIDAD]]*Tabla8[[#This Row],[PRECIO]] -> 27 | G116: PROVISION | I116: =UPPER(TEXT(A116,"MMMM")) -> FEBRERO | J116: =+YEAR(A116) -> 2026 | K116: PICHINCHA
A117: 46059 | B117: DANNA | C117: PERSONAL | D117: 1 | E117: 32.5 | F117: =Tabla8[[#This Row],[CANTIDAD]]*Tabla8[[#This Row],[PRECIO]] -> 32.5 | G117: ADELANTO DANNA | I117: =UPPER(TEXT(A117,"MMMM")) -> FEBRERO | J117: =+YEAR(A117) -> 2026 | K117: PICHINCHA
A118: 46059 | B118: DEPOSITO | C118: CRUCE CUENTAS | D118: 1 | E118: 40 | F118: =Tabla8[[#This Row],[CANTIDAD]]*Tabla8[[#This Row],[PRECIO]] -> 40 | G118: CRUCE CUENTAS DE UNA-PICHINCHA | I118: =UPPER(TEXT(A118,"MMMM")) -> FEBRERO | J118: =+YEAR(A118) -> 2026 | K118: PICHINCHA | L118: DE UNA
A119: 46060 | B119: COMIDA | C119: PERSONAL | D119: 1 | E119: 4 | F119: =Tabla8[[#This Row],[CANTIDAD]]*Tabla8[[#This Row],[PRECIO]] -> 4 | G119: MOTO BRYAM | I119: =UPPER(TEXT(A119,"MMMM")) -> FEBRERO | J119: =+YEAR(A119) -> 2026 | K119: EFECTIVO
A120: 46061 | B120: DANNA | C120: PERSONAL | D120: 1 | E120: 30 | F120: =Tabla8[[#This Row],[CANTIDAD]]*Tabla8[[#This Row],[PRECIO]] -> 30 | G120: ADELANTO DANNA | I120: =UPPER(TEXT(A120,"MMMM")) -> FEBRERO | J120: =+YEAR(A120) -> 2026 | K120: EFECTIVO
A121: 46062 | B121: COMIDA | C121: PERSONAL | D121: 1 | E121: 2.5 | F121: =Tabla8[[#This Row],[CANTIDAD]]*Tabla8[[#This Row],[PRECIO]] -> 2.5 | G121: COMIDA DANNA Y BRYAM | I121: =UPPER(TEXT(A121,"MMMM")) -> FEBRERO | J121: =+YEAR(A121) -> 2026 | K121: PICHINCHA | L121: DE UNA
A122: 46063 | B122: DEPOSITO | C122: OPTICA | D122: 1 | E122: 50 | F122: =Tabla8[[#This Row],[CANTIDAD]]*Tabla8[[#This Row],[PRECIO]] -> 50 | G122: DEPOSITO BANCO | I122: =UPPER(TEXT(A122,"MMMM")) -> FEBRERO | J122: =+YEAR(A122) -> 2026 | K122: EFECTIVO
A123: 46063 | B123: COMPRAS | C123: OPTICA | D123: 1 | E123: 6.21 | F123: =Tabla8[[#This Row],[CANTIDAD]]*Tabla8[[#This Row],[PRECIO]] -> 6.21 | G123: COMPRAS CYC | I123: =UPPER(TEXT(A123,"MMMM")) -> FEBRERO | J123: =+YEAR(A123) -> 2026 | K123: PICHINCHA
A124: 46065 | B124: COMIDA | C124: PERSONAL | D124: 1 | E124: 5 | F124: =Tabla8[[#This Row],[CANTIDAD]]*Tabla8[[#This Row],[PRECIO]] -> 5 | G124: COMIAD FRUTAS | I124: =UPPER(TEXT(A124,"MMMM")) -> FEBRERO | J124: =+YEAR(A124) -> 2026 | K124: EFECTIVO
A125: 46065 | B125: BRYAM | C125: PERSONAL | D125: 1 | E125: 40 | F125: =Tabla8[[#This Row],[CANTIDAD]]*Tabla8[[#This Row],[PRECIO]] -> 40 | G125: ADELANTO BRYAM | I125: =UPPER(TEXT(A125,"MMMM")) -> FEBRERO | J125: =+YEAR(A125) -> 2026 | K125: EFECTIVO
A126: 46065 | B126: COMIDA | C126: PERSONAL | D126: 1 | E126: 1.2 | F126: =Tabla8[[#This Row],[CANTIDAD]]*Tabla8[[#This Row],[PRECIO]] -> 1.2 | G126: COMIDA | I126: =UPPER(TEXT(A126,"MMMM")) -> FEBRERO | J126: =+YEAR(A126) -> 2026 | K126: EFECTIVO
A127: 46065 | B127: DANNA | C127: PERSONAL | D127: 1 | E127: 15 | F127: =Tabla8[[#This Row],[CANTIDAD]]*Tabla8[[#This Row],[PRECIO]] -> 15 | G127: ADELANTO DANNA | I127: =UPPER(TEXT(A127,"MMMM")) -> FEBRERO | J127: =+YEAR(A127) -> 2026 | K127: PICHINCHA
A128: 46066 | B128: COMPRAS | C128: OPTICA | D128: 1 | E128: 18 | F128: =Tabla8[[#This Row],[CANTIDAD]]*Tabla8[[#This Row],[PRECIO]] -> 18 | G128: COSAS DE LIMPIEZA | I128: =UPPER(TEXT(A128,"MMMM")) -> FEBRERO | J128: =+YEAR(A128) -> 2026 | K128: EFECTIVO
A129: 46066 | B129: BRYAM | C129: PERSONAL | D129: 1 | E129: 4 | F129: =Tabla8[[#This Row],[CANTIDAD]]*Tabla8[[#This Row],[PRECIO]] -> 4 | G129: ADELANTO BRYAM | I129: =UPPER(TEXT(A129,"MMMM")) -> FEBRERO | J129: =+YEAR(A129) -> 2026 | K129: EFECTIVO
A130: 46066 | B130: DANNA | C130: PERSONAL | D130: 1 | E130: 18 | F130: =Tabla8[[#This Row],[CANTIDAD]]*Tabla8[[#This Row],[PRECIO]] -> 18 | G130: ADELANTO DANNA | I130: =UPPER(TEXT(A130,"MMMM")) -> FEBRERO | J130: =+YEAR(A130) -> 2026 | K130: PICHINCHA
A131: 46066 | B131: COMIDA | C131: PERSONAL | D131: 1 | E131: 10 | F131: =Tabla8[[#This Row],[CANTIDAD]]*Tabla8[[#This Row],[PRECIO]] -> 10 | G131: ALMUERZO DANNA Y BRYAM | I131: =UPPER(TEXT(A131,"MMMM")) -> FEBRERO | J131: =+YEAR(A131) -> 2026 | K131: EFECTIVO
A132: 46066 | B132: BRYAM | C132: PERSONAL | D132: 1 | E132: 1 | F132: =Tabla8[[#This Row],[CANTIDAD]]*Tabla8[[#This Row],[PRECIO]] -> 1 | G132: BRYAM | I132: =UPPER(TEXT(A132,"MMMM")) -> FEBRERO | J132: =+YEAR(A132) -> 2026 | K132: EFECTIVO
A133: 46066 | B133: COMIDA | C133: PERSONAL | D133: 1 | E133: 20 | F133: =Tabla8[[#This Row],[CANTIDAD]]*Tabla8[[#This Row],[PRECIO]] -> 20 | G133: ALMUERZO DANNA Y BRYAM | I133: =UPPER(TEXT(A133,"MMMM")) -> FEBRERO | J133: =+YEAR(A133) -> 2026 | K133: EFECTIVO
... A136: 46067 | B136: MOTORIZADO | C136: OPTICA | D136: 1 | E136: 2 | F136: =Tabla8[[#This Row],[CANTIDAD]]*Tabla8[[#This Row],[PRECIO]] -> 2 | G136: MOTO BRYAM | I136: =UPPER(TEXT(A136,"MMMM")) -> FEBRERO | J136: =+YEAR(A136) -> 2026 | K136: EFECTIVO
A137: 46068 | B137: DANNA | C137: PERSONAL | D137: 1 | E137: 15 | F137: =Tabla8[[#This Row],[CANTIDAD]]*Tabla8[[#This Row],[PRECIO]] -> 15 | G137: ADELANTO DANNA | I137: =UPPER(TEXT(A137,"MMMM")) -> FEBRERO | J137: =+YEAR(A137) -> 2026 | K137: PICHINCHA | L137: DE UNA
A138: 46071 | B138: DANNA | C138: PERSONAL | D138: 1 | E138: 20 | F138: =Tabla8[[#This Row],[CANTIDAD]]*Tabla8[[#This Row],[PRECIO]] -> 20 | G138: ADELANTO DANNA | I138: =UPPER(TEXT(A138,"MMMM")) -> FEBRERO | J138: =+YEAR(A138) -> 2026 | K138: PICHINCHA | L138: DE UNA
A139: 46071 | B139: DEPOSITO | C139: PERSONAL | D139: 1 | E139: 100 | F139: =Tabla8[[#This Row],[CANTIDAD]]*Tabla8[[#This Row],[PRECIO]] -> 100 | G139: PRESTAMO DIEGO MORA | I139: =UPPER(TEXT(A139,"MMMM")) -> FEBRERO | J139: =+YEAR(A139) -> 2026 | K139: EFECTIVO
A140: 46072 | B140: COMIDA | C140: PERSONAL | D140: 1 | E140: 20 | F140: =Tabla8[[#This Row],[CANTIDAD]]*Tabla8[[#This Row],[PRECIO]] -> 20 | G140: COMIDA DANNA Y BRYAM | I140: =UPPER(TEXT(A140,"MMMM")) -> FEBRERO | J140: =+YEAR(A140) -> 2026 | K140: EFECTIVO
A141: 46072 | B141: COMIDA | C141: PERSONAL | D141: 1 | E141: 8.3 | F141: =Tabla8[[#This Row],[CANTIDAD]]*Tabla8[[#This Row],[PRECIO]] -> 8.3 | G141: COMIDA DANNA Y BRYAM | I141: =UPPER(TEXT(A141,"MMMM")) -> FEBRERO | J141: =+YEAR(A141) -> 2026 | K141: EFECTIVO
A142: 46073 | B142: COMIDA | C142: PERSONAL | D142: 1 | E142: 6.9 | F142: =Tabla8[[#This Row],[CANTIDAD]]*Tabla8[[#This Row],[PRECIO]] -> 6.9 | G142: COMIDA DANNA Y BRYAM | I142: =UPPER(TEXT(A142,"MMMM")) -> FEBRERO | J142: =+YEAR(A142) -> 2026 | K142: EFECTIVO
A143: 46073 | B143: MOTORIZADO | C143: OPTICA | D143: 1 | E143: 5 | F143: =Tabla8[[#This Row],[CANTIDAD]]*Tabla8[[#This Row],[PRECIO]] -> 5 | G143: MOTORIZADO | I143: =UPPER(TEXT(A143,"MMMM")) -> FEBRERO | J143: =+YEAR(A143) -> 2026 | K143: EFECTIVO
A144: 46076 | B144: COMIDA | C144: PERSONAL | D144: 1 | E144: 4 | F144: =Tabla8[[#This Row],[CANTIDAD]]*Tabla8[[#This Row],[PRECIO]] -> 4 | G144: COMIDA DANNA Y BRYAM | I144: =UPPER(TEXT(A144,"MMMM")) -> FEBRERO | J144: =+YEAR(A144) -> 2026 | K144: EFECTIVO
A145: 46077 | B145: AGUA | C145: OPTICA | D145: 1 | E145: 7.15 | F145: =Tabla8[[#This Row],[CANTIDAD]]*Tabla8[[#This Row],[PRECIO]] -> 7.15 | G145: AGUA BOTELLONES | I145: =UPPER(TEXT(A145,"MMMM")) -> FEBRERO | J145: 2026 | K145: EFECTIVO
A146: 46079 | B146: DEPOSITO | C146: OPTICA | D146: 1 | E146: 10 | F146: =Tabla8[[#This Row],[CANTIDAD]]*Tabla8[[#This Row],[PRECIO]] -> 10 | G146: CRUCE CUENTAS PICHINCHA | I146: =UPPER(TEXT(A146,"MMMM")) -> FEBRERO | J146: =+YEAR(A146) -> 2026 | K146: EFECTIVO
A147: 46079 | B147: MOTORIZADO | C147: OPTICA | D147: 1 | E147: 6 | F147: =Tabla8[[#This Row],[CANTIDAD]]*Tabla8[[#This Row],[PRECIO]] -> 6 | G147: MOTORIZADO | I147: =UPPER(TEXT(A147,"MMMM")) -> FEBRERO | J147: =+YEAR(A147) -> 2026 | K147: EFECTIVO
A148: 46079 | B148: COMIDA | C148: PERSONAL | D148: 1 | E148: 1 | F148: =Tabla8[[#This Row],[CANTIDAD]]*Tabla8[[#This Row],[PRECIO]] -> 1 | G148: YOGURT BRYAM | I148: =UPPER(TEXT(A148,"MMMM")) -> FEBRERO | J148: =+YEAR(A148) -> 2026 | K148: EFECTIVO
A149: 46080 | B149: COMPRAS | C149: OPTICA | D149: 1 | E149: 5 | F149: =Tabla8[[#This Row],[CANTIDAD]]*Tabla8[[#This Row],[PRECIO]] -> 5 | G149: FUNDAS DE BASURA | I149: =UPPER(TEXT(A149,"MMMM")) -> FEBRERO | J149: =+YEAR(A149) -> 2026 | K149: EFECTIVO
A150: 46080 | B150: COMPRAS | C150: PERSONAL | D150: 1 | E150: 650 | F150: =Tabla8[[#This Row],[CANTIDAD]]*Tabla8[[#This Row],[PRECIO]] -> 650 | G150: COLCHON Y SABANAS | I150: =UPPER(TEXT(A150,"MMMM")) -> FEBRERO | J150: =+YEAR(A150) -> 2026 | K150: EFECTIVO
A151: 46080 | B151: COMPRAS | C151: PERSONAL | D151: 1 | E151: 24.36 | F151: =Tabla8[[#This Row],[CANTIDAD]]*Tabla8[[#This Row],[PRECIO]] -> 24.36 | G151: COMIDA VIERNES WAYRA | I151: =UPPER(TEXT(A151,"MMMM")) -> FEBRERO | J151: =+YEAR(A151) -> 2026 | K151: EFECTIVO
A152: 46081 | B152: COMPRAS | C152: PERSONAL | D152: 1 | E152: 20.3 | F152: =Tabla8[[#This Row],[CANTIDAD]]*Tabla8[[#This Row],[PRECIO]] -> 20.3 | G152: COMIDA FIN DE SEMANA | I152: =UPPER(TEXT(A152,"MMMM")) -> FEBRERO | J152: =+YEAR(A152) -> 2026 | K152: EFECTIVO
A153: 46083 | B153: COMIDA | C153: PERSONAL | D153: 1 | E153: 10 | F153: =Tabla8[[#This Row],[CANTIDAD]]*Tabla8[[#This Row],[PRECIO]] -> 10 | G153: COMIDA DOMINGO | I153: =UPPER(TEXT(A153,"MMMM")) -> MARZO | J153: =+YEAR(A153) -> 2026 | K153: EFECTIVO
A154: 46083 | B154: DANNA | C154: PERSONAL | D154: 1 | E154: 60 | F154: =Tabla8[[#This Row],[CANTIDAD]]*Tabla8[[#This Row],[PRECIO]] -> 60 | G154: ADELANTO DANNA | I154: =UPPER(TEXT(A154,"MMMM")) -> MARZO | J154: =+YEAR(A154) -> 2026 | K154: EFECTIVO
A155: 03/02/2026 | B155: COMPRAS | C155: OPTICA | D155: 1 | E155: 2.5 | F155: =Tabla8[[#This Row],[CANTIDAD]]*Tabla8[[#This Row],[PRECIO]] -> 2.5 | G155: PAÑITOS HUMEDOS | I155: MARZO | J155: 2026 | K155: EFECTIVO
A156: 46085 | B156: BRYAM | C156: PERSONAL | D156: 1 | E156: 200 | F156: =Tabla8[[#This Row],[CANTIDAD]]*Tabla8[[#This Row],[PRECIO]] -> 200 | G156: PLAYA( PENDIENTE DEVOLUCION) | I156: =UPPER(TEXT(A156,"MMMM")) -> MARZO | J156: =+YEAR(A156) -> 2026 | K156: EFECTIVO
A157: 46085 | B157: COMIDA | C157: PERSONAL | D157: 1 | E157: 4 | F157: =Tabla8[[#This Row],[CANTIDAD]]*Tabla8[[#This Row],[PRECIO]] -> 4 | G157: CAFÉ CON PAN | I157: =UPPER(TEXT(A157,"MMMM")) -> MARZO | J157: =+YEAR(A157) -> 2026 | K157: EFECTIVO
A158: 46085 | B158: COMPRAS | C158: PERSONAL | D158: 1 | E158: 20 | F158: =Tabla8[[#This Row],[CANTIDAD]]*Tabla8[[#This Row],[PRECIO]] -> 20 | G158: AYUDA SOCIAL | I158: =UPPER(TEXT(A158,"MMMM")) -> MARZO | J158: =+YEAR(A158) -> 2026 | K158: EFECTIVO
A159: 46091 | F159: =Tabla8[[#This Row],[CANTIDAD]]*Tabla8[[#This Row],[PRECIO]] -> 0 | I159: =UPPER(TEXT(A159,"MMMM")) -> MARZO | J159: =+YEAR(A159) -> 2026
A160: 46092 | F160: =Tabla8[[#This Row],[CANTIDAD]]*Tabla8[[#This Row],[PRECIO]] -> 0 | I160: =UPPER(TEXT(A160,"MMMM")) -> MARZO | J160: =+YEAR(A160) -> 2026
A161: 46093 | F161: =Tabla8[[#This Row],[CANTIDAD]]*Tabla8[[#This Row],[PRECIO]] -> 0 | I161: =UPPER(TEXT(A161,"MMMM")) -> MARZO | J161: =+YEAR(A161) -> 2026
A162: 46094 | F162: =Tabla8[[#This Row],[CANTIDAD]]*Tabla8[[#This Row],[PRECIO]] -> 0 | I162: =UPPER(TEXT(A162,"MMMM")) -> MARZO | J162: =+YEAR(A162) -> 2026
A163: 46095 | F163: =Tabla8[[#This Row],[CANTIDAD]]*Tabla8[[#This Row],[PRECIO]] -> 0 | I163: =UPPER(TEXT(A163,"MMMM")) -> MARZO | J163: =+YEAR(A163) -> 2026
A164: 46096 | F164: =Tabla8[[#This Row],[CANTIDAD]]*Tabla8[[#This Row],[PRECIO]] -> 0 | I164: =UPPER(TEXT(A164,"MMMM")) -> MARZO | J164: =+YEAR(A164) -> 2026
A165: 46097 | F165: =Tabla8[[#This Row],[CANTIDAD]]*Tabla8[[#This Row],[PRECIO]] -> 0 | I165: =UPPER(TEXT(A165,"MMMM")) -> MARZO | J165: =+YEAR(A165) -> 2026
A166: 46098 | F166: =Tabla8[[#This Row],[CANTIDAD]]*Tabla8[[#This Row],[PRECIO]] -> 0 | I166: =UPPER(TEXT(A166,"MMMM")) -> MARZO | J166: =+YEAR(A166) -> 2026

Sheet FACTURAS
E1: DIARIO DE FACTURAS
A3: FECHA | B3: CUENTA | C3: DISTRIBUIDOR | D3: TOTAL | E3: DETALLE ADICIONAL | F3: NO. DOCUMENTO | G3: MES | H3: AÑO | I3: TIPO DE PAGO
A4: 46028 | B4: POR PAGAR | C4: IMPORTLENTS | D4: 25.9 | E4: LUNAS Y BISEL PARA JOSE LEON | F4: 62352 | G4: =UPPER(TEXT(A4,"MMMM")) -> ENERO | H4: =+YEAR(A4) -> 2026
A5: 46028 | B5: POR PAGAR | C5: IMPORTLENTS | D5: 31.51 | E5: LUNAS Y BISEL PARA BYRON AYALA | F5: 62355 | G5: =UPPER(TEXT(A5,"MMMM")) -> ENERO | H5: =+YEAR(A5) -> 2026
A6: 46029 | B6: POR PAGAR | C6: IMPORTLENTS | D6: 29.26 | E6: LUNAS Y BISEL PARA ANAHI PINOS | F6: 62416 | G6: =UPPER(TEXT(A6,"MMMM")) -> ENERO | H6: =+YEAR(A6) -> 2026
A7: 46029 | B7: POR PAGAR | C7: IMPORTLENTS | D7: 31.35 | E7: LUNAS Y BISEL NANCY AMENDAÑO Y FABIAN MARIN | F7: 62425 | G7: =UPPER(TEXT(A7,"MMMM")) -> ENERO | H7: =+YEAR(A7) -> 2026
A8: 46029 | B8: POR PAGAR | C8: IMPORTLENTS | D8: 23.9 | E8: LUNAS LUZ VASQUEZ | F8: 62427 | G8: =UPPER(TEXT(A8,"MMMM")) -> ENERO | H8: =+YEAR(A8) -> 2026
A9: 46030 | B9: POR PAGAR | C9: OPTEC | D9: 24.15 | E9: LUNA TERMINADA TRANSITION GRIS DAVID RODRIGUEZ | F9: 928780 | G9: =UPPER(TEXT(A9,"MMMM")) -> ENERO | H9: =+YEAR(A9) -> 2026
A10: 46030 | B10: POR PAGAR | C10: OPTEC | D10: 41.4 | E10: LUNA TALLADA TRANSITION GRIS DAVID RODRIGUEZ | F10: 92782 | G10: =UPPER(TEXT(A10,"MMMM")) -> ENERO | H10: =+YEAR(A10) -> 2026
A11: 46031 | B11: POR PAGAR | C11: IMPORTLENTS | D11: 2.1 | E11: BISEL | F11: 62552 | G11: =UPPER(TEXT(A11,"MMMM")) -> ENERO | H11: =+YEAR(A11) -> 2026
A12: 46031 | B12: PAGADO | C12: PECSA | D12: 52.23 | E12: LUNAS PECSA PRECISA BLUE +AR EULALIA GALINDO | F12: 2354 | G12: =UPPER(TEXT(A12,"MMMM")) -> ENERO | H12: =+YEAR(A12) -> 2026
A13: 46032 | B13: POR PAGAR | C13: IMPORTLENTS | D13: 2.6 | E13: BISEL BIFOCAL | F13: 62590 | G13: =UPPER(TEXT(A13,"MMMM")) -> ENERO | H13: =+YEAR(A13) -> 2026
A14: 46034 | B14: POR PAGAR | C14: IMPORTLENTS | D14: 1 | E14: BISEL | F14: 62630 | G14: =UPPER(TEXT(A14,"MMMM")) -> ENERO | H14: =+YEAR(A14) -> 2026
A15: 46034 | B15: POR PAGAR | C15: IMPORTLENTS | D15: 27 | E15: LUNAS Y BISEL VANESSA PESANTEZ | F15: 62660 | G15: =UPPER(TEXT(A15,"MMMM")) -> ENERO | H15: =+YEAR(A15) -> 2026
... A43: 46058 | B43: POR PAGAR | C43: IMPORTLENTS | D43: 20.52 | E43: LUNAS POLI AR- LUIS BRAVO | F43: 63735 | G43: =UPPER(TEXT(A43,"MMMM")) -> FEBRERO | H43: =+YEAR(A43) -> 2026
A44: 46058 | B44: POR PAGAR | C44: IMPORTLENTS | D44: * | E44: LUNAS AR - PAUL SUÑA | F44: 63735 | G44: =UPPER(TEXT(A44,"MMMM")) -> FEBRERO | H44: =+YEAR(A44) -> 2026
A45: 46059 | B45: POR PAGAR | C45: IMPORTLENTS | D45: 2.4 | E45: LUNAS BLUE AR | F45: 63809 | G45: =UPPER(TEXT(A45,"MMMM")) -> FEBRERO | H45: =+YEAR(A45) -> 2026
A46: 46059 | B46: POR PAGAR | C46: IMPORTLENTS | D46: 5.41 | E46: LUNAS POLY AR AMELIA MOGROVEJO | F46: 63785 | G46: =UPPER(TEXT(A46,"MMMM")) -> FEBRERO | H46: =+YEAR(A46) -> 2026
A47: 46059 | B47: POR PAGAR | C47: OPTEC | D47: 55.2 | E47: LUNAS-POLI-POLARIZADO- MIRIAM SEGOVIA | F47: 939548 | G47: =UPPER(TEXT(A47,"MMMM")) -> FEBRERO | H47: =+YEAR(A47) -> 2026
A48: 46060 | B48: POR PAGAR | C48: IMPORTLENTS | D48: 5.41 | E48: LUNAS POLI AR-ROSA AREVALO | F48: 63871 | G48: =UPPER(TEXT(A48,"MMMM")) -> FEBRERO | H48: =+YEAR(A48) -> 2026
A49: 46063 | B49: POR PAGAR | C49: IMPORTLENTS | D49: 3.99 | E49: BISEL POLY BLANCO Y TRASPASO | F49: 63974 | G49: =UPPER(TEXT(A49,"MMMM")) -> FEBRERO | H49: =+YEAR(A49) -> 2026
A50: 46065 | B50: POR PAGAR | C50: IMPORTLENTS | D50: * | E50: LUNAS ANTIREFLEJO ROCIO LITUMA Y BISEL | F50: 54053 | G50: =UPPER(TEXT(A50,"MMMM")) -> FEBRERO | H50: =+YEAR(A50) -> 2026
A51: 46065 | B51: POR PAGAR | C51: IMPORTLENTS | D51: 9.89 | E51: ARM. METAL CRONOS Y TRASPASO | F51: 54058 | G51: =UPPER(TEXT(A51,"MMMM")) -> FEBRERO | H51: =+YEAR(A51) -> 2026
A52: 46067 | B52: POR PAGAR | C52: IMPORTLENTS | D52: 62.01 | E52: LUNAS Y BISEL PEDRO CHALCO GX7 (4 LUNAS) | F52: 54142 | G52: =UPPER(TEXT(A52,"MMMM")) -> FEBRERO | H52: =+YEAR(A52) -> 2026
A53: 46067 | B53: POR PAGAR | C53: IMPORTLENTS | D53: * | E53: TRASPASO | F53: 54142 | G53: =UPPER(TEXT(A53,"MMMM")) -> FEBRERO | H53: =+YEAR(A53) -> 2026
A54: 46071 | B54: POR PAGAR | C54: OPTEC | D54: 115 | E54: LUNAS POLI-PRO KODAK ZAFIRO-BERTHA GUILLEN | F54: 942678 | G54: =UPPER(TEXT(A54,"MMMM")) -> FEBRERO | H54: =+YEAR(A54) -> 2026
A55: 46072 | B55: POR PAGAR | C55: IMPORTLENTS | D55: 13.31 | E55: BISELADOS GX7 Y POLY BLUE AR | F55: 10013571 | G55: =UPPER(TEXT(A55,"MMMM")) -> FEBRERO | H55: =+YEAR(A55) -> 2026
A56: 46072 | B56: PAGADO | C56: PECSA | D56: 46.21 | E56: PROGRESIVO BLUE BLOCK + AR -EDUARDO CANDO | F56: 81002 | G56: =UPPER(TEXT(A56,"MMMM")) -> FEBRERO | H56: =+YEAR(A56) -> 2026
A57: 46072 | B57: PAGADO | C57: PECSA | D57: 51.21 | E57: PROGRESIVO BLUE BLOCK + AR -EDUARDO CANDO | F57: 81001 | G57: =UPPER(TEXT(A57,"MMMM")) -> FEBRERO | H57: =+YEAR(A57) -> 2026
A58: 46073 | B58: POR PAGAR | C58: IMPORTLENTS | D58: 22.1 | E58: LUNAS FABIO MOROCHO GX7 BLUE AR Y BISEL | F58: 10013590 | G58: =UPPER(TEXT(A58,"MMMM")) -> FEBRERO | H58: =+YEAR(A58) -> 2026
A59: 46073 | B59: POR PAGAR | C59: IMPORTLENTS | D59: 27 | E59: LUNAS GX7 BLUE AR MICHELLE ZAMORA | F59: 10013603 | G59: =UPPER(TEXT(A59,"MMMM")) -> FEBRERO | H59: =+YEAR(A59) -> 2026
A60: 46073 | B60: POR PAGAR | C60: IMPORTLENTS | D60: 11.01 | E60: L/C VERDE - DAYANA MOROCHO | F60: 10013604 | G60: =UPPER(TEXT(A60,"MMMM")) -> FEBRERO | H60: =+YEAR(A60) -> 2026
A61: 46074 | B61: PAGADO | C61: PROVISION LENS | D61: 10 | E61: LUNAS POLY-BLANCO - JUAN DIEGO MOROCHO | F61: 8565 | G61: =UPPER(TEXT(A61,"MMMM")) -> FEBRERO | H61: =+YEAR(A61) -> 2026
A62: 46077 | B62: POR PAGAR | C62: OPTEC | D62: 110.4 | E62: LUNAS POLI VARILUX BLUE AR- HUMBERTO PARRAGA | F62: 945145 | G62: =UPPER(TEXT(A62,"MMMM")) -> FEBRERO | H62: =+YEAR(A62) -> 2026
A63: 46079 | B63: POR PAGAR | C63: IMPORTLENTS | D63: 7.05 | E63: LUNAS POLI-AR - ANDRES LEON | F63: 13684 | G63: =UPPER(TEXT(A63,"MMMM")) -> FEBRERO | H63: =+YEAR(A63) -> 2026
A64: 46079 | B64: PAGADO | C64: PECSA | D64: 46.21 | E64: LUNAS PROGRESIVAS BLUE + AR- SANTIAGO ESPINOZA | F64: 3798 | G64: =UPPER(TEXT(A64,"MMMM")) -> FEBRERO | H64: =+YEAR(A64) -> 2026
A65: 46079 | B65: PAGADO | C65: PECSA | D65: 41.07 | E65: PROGRESIVAS ELITE HD BLUE+AR- SORAYA CRIOLLO | F65: 3800 | G65: =UPPER(TEXT(A65,"MMMM")) -> FEBRERO | H65: =+YEAR(A65) -> 2026
... A67: 46079 | B67: PAGADO | C67: PECSA | D67: 46.21 | E67: PROGRESIVAS BLUE BLOCK + AR-EDGAR GUY | F67: 3799 | G67: =UPPER(TEXT(A67,"MMMM")) -> FEBRERO | H67: =+YEAR(A67) -> 2026
A68: 46083 | G68: =UPPER(TEXT(A68,"MMMM")) -> MARZO | H68: =+YEAR(A68) -> 2026
A69: 46084 | B69: POR PAGAR | C69: IMPORTLENTS | D69: 23.9 | E69: GX7-BLUE AR-ERIKA ARIAS | F69: 64776 | G69: =UPPER(TEXT(A69,"MMMM")) -> MARZO | H69: =+YEAR(A69) -> 2026
A70: 46084 | G70: =UPPER(TEXT(A70,"MMMM")) -> MARZO | H70: =+YEAR(A70) -> 2026
A71: 46085 | G71: =UPPER(TEXT(A71,"MMMM")) -> MARZO | H71: =+YEAR(A71) -> 2026
A72: 46086 | G72: =UPPER(TEXT(A72,"MMMM")) -> MARZO | H72: =+YEAR(A72) -> 2026
H73: 2026

Sheet RESUMEN 1
A3: AÑO | B3: REGISTRO DE INGRESOS Y EGRESOS
A5: 2026 | B5: TIPO | C5: ENERO | D5: FEBRERO | E5: MARZO | F5: ABRIL | G5: MAYO | H5: JUNIO | I5: JULIO | J5: AGOSTO | K5: SEPTIEMBRE | L5: OCTUBRE | M5: NOVIEMBRE | N5: DICIEMBRE
A6: INGRESOS | B6: EFECTIVO | C6: =SUMIFS(Tabla5[INGRESO],Tabla5[MES],'RESUMEN 1'!C5,Tabla5[AÑO],'RESUMEN 1'!A5,Tabla5[TIPO DE PAGO],'RESUMEN 1'!B6) -> 6101.86 | D6: =SUMIFS(Tabla5[INGRESO],Tabla5[MES],'RESUMEN 1'!D5,Tabla5[AÑO],'RESUMEN 1'!A5,Tabla5[TIPO DE PAGO],'RESUMEN 1'!B6) -> 2220 | L6: =SUMIFS(Tabla5[INGRESO],Tabla5[MES],'RESUMEN 1'!L5,Tabla5[AÑO],'RESUMEN 1'!A5,Tabla5[TIPO DE PAGO],'RESUMEN 1'!B6) -> 0 | M6: =SUMIFS(Tabla5[INGRESO],Tabla5[MES],'RESUMEN 1'!M5,Tabla5[AÑO],'RESUMEN 1'!A5,Tabla5[TIPO DE PAGO],'RESUMEN 1'!B6) -> 0
A7: INGRESOS | B7: TARJETA | C7: =SUMIFS(Tabla5[INGRESO],Tabla5[MES],'RESUMEN 1'!C5,Tabla5[AÑO],'RESUMEN 1'!A5,Tabla5[TIPO DE PAGO],'RESUMEN 1'!B7) -> 0 | L7: =SUMIFS(Tabla5[INGRESO],Tabla5[MES],'RESUMEN 1'!L5,Tabla5[AÑO],'RESUMEN 1'!A5,Tabla5[TIPO DE PAGO],'RESUMEN 1'!B7) -> 0 | M7: =SUMIFS(Tabla5[INGRESO],Tabla5[MES],'RESUMEN 1'!M5,Tabla5[AÑO],'RESUMEN 1'!A5,Tabla5[TIPO DE PAGO],'RESUMEN 1'!B7) -> 0
A8: INGRESOS | B8: JEP DANNA | C8: =SUMIFS(Tabla5[INGRESO],Tabla5[MES],'RESUMEN 1'!C5,Tabla5[AÑO],'RESUMEN 1'!A5,Tabla5[TIPO DE PAGO],'RESUMEN 1'!B8)+SUMIFS(Tabla8[EGRESO],Tabla8[CUENTA],"DEPOSITO",Tabla8[DISTRIBUIDOR],'RESUMEN 1'!B8) -> 50 | D8: =SUMIFS(Tabla5[INGRESO],Tabla5[MES],'RESUMEN 1'!D5,Tabla5[AÑO],'RESUMEN 1'!A5,Tabla5[TIPO DE PAGO],'RESUMEN 1'!B8)+SUMIFS(Tabla8[EGRESO],Tabla8[CUENTA],"DEPOSITO",Tabla8[DISTRIBUIDOR],'RESUMEN 1'!B8) -> 396.76 | L8: =SUMIFS(Tabla5[INGRESO],Tabla5[MES],'RESUMEN 1'!L5,Tabla5[AÑO],'RESUMEN 1'!A5,Tabla5[TIPO DE PAGO],'RESUMEN 1'!B8) -> 0 | M8: =SUMIFS(Tabla5[INGRESO],Tabla5[MES],'RESUMEN 1'!M5,Tabla5[AÑO],'RESUMEN 1'!A5,Tabla5[TIPO DE PAGO],'RESUMEN 1'!B8) -> 0
A9: INGRESOS | B9: PICHINCHA | C9: =SUMIFS(Tabla5[INGRESO],Tabla5[MES],'RESUMEN 1'!C5,Tabla5[AÑO],'RESUMEN 1'!A5,Tabla5[TIPO DE PAGO],'RESUMEN 1'!B9)+SUMIFS(Tabla8[EGRESO],Tabla8[CUENTA],"DEPOSITO",Tabla8[DISTRIBUIDOR],'RESUMEN 1'!B9) -> 1891.59 | D9: =SUMIFS(Tabla5[INGRESO],Tabla5[MES],'RESUMEN 1'!D5,Tabla5[AÑO],'RESUMEN 1'!A5,Tabla5[TIPO DE PAGO],'RESUMEN 1'!B9)+SUMIFS(Tabla8[EGRESO],Tabla8[CUENTA],"DEPOSITO",Tabla8[DISTRIBUIDOR],'RESUMEN 1'!B9) -> 1534.43 | L9: =SUMIFS(Tabla5[INGRESO],Tabla5[MES],'RESUMEN 1'!L5,Tabla5[AÑO],'RESUMEN 1'!A5,Tabla5[TIPO DE PAGO],'RESUMEN 1'!B9) -> 0 | M9: =SUMIFS(Tabla5[INGRESO],Tabla5[MES],'RESUMEN 1'!M5,Tabla5[AÑO],'RESUMEN 1'!A5,Tabla5[TIPO DE PAGO],'RESUMEN 1'!B9) -> 0
A10: INGRESOS | B10: PRODUBANCO | C10: =SUMIFS(Tabla5[INGRESO],Tabla5[MES],'RESUMEN 1'!C5,Tabla5[AÑO],'RESUMEN 1'!A5,Tabla5[TIPO DE PAGO],'RESUMEN 1'!B10)+SUMIFS(Tabla8[EGRESO],Tabla8[CUENTA],"DEPOSITO",Tabla8[DISTRIBUIDOR],'RESUMEN 1'!B10) -> 0 | L10: =SUMIFS(Tabla5[INGRESO],Tabla5[MES],'RESUMEN 1'!L5,Tabla5[AÑO],'RESUMEN 1'!A5,Tabla5[TIPO DE PAGO],'RESUMEN 1'!B10) -> 0 | M10: =SUMIFS(Tabla5[INGRESO],Tabla5[MES],'RESUMEN 1'!M5,Tabla5[AÑO],'RESUMEN 1'!A5,Tabla5[TIPO DE PAGO],'RESUMEN 1'!B10) -> 0
A11: INGRESOS | B11: JARDIN AZUAYO | C11: =SUMIFS(Tabla5[INGRESO],Tabla5[MES],'RESUMEN 1'!C5,Tabla5[AÑO],'RESUMEN 1'!A5,Tabla5[TIPO DE PAGO],'RESUMEN 1'!B11)+SUMIFS(Tabla8[EGRESO],Tabla8[CUENTA],"DEPOSITO",Tabla8[DISTRIBUIDOR],'RESUMEN 1'!B11) -> 0 | L11: =SUMIFS(Tabla5[DESCRIPCION],Tabla5[AÑO],'RESUMEN 1'!L5,Tabla5[FECHA],'RESUMEN 1'!A5,Tabla5[MES],'RESUMEN 1'!B11) -> 0 | M11: =SUMIFS(Tabla5[DESCRIPCION],Tabla5[AÑO],'RESUMEN 1'!M5,Tabla5[FECHA],'RESUMEN 1'!A5,Tabla5[MES],'RESUMEN 1'!B11) -> 0
A12: INGRESOS | B12: JEP BRYAM | C12: =SUMIFS(Tabla5[INGRESO],Tabla5[MES],'RESUMEN 1'!C5,Tabla5[AÑO],'RESUMEN 1'!A5,Tabla5[TIPO DE PAGO],'RESUMEN 1'!B12)+SUMIFS(Tabla8[EGRESO],Tabla8[CUENTA],"DEPOSITO",Tabla8[DISTRIBUIDOR],'RESUMEN 1'!B12) -> 0 | L12: =SUMIFS(Tabla5[INGRESO],Tabla5[MES],'RESUMEN 1'!L5,Tabla5[AÑO],'RESUMEN 1'!A5,Tabla5[TIPO DE PAGO],'RESUMEN 1'!B12) -> 0 | M12: =SUMIFS(Tabla5[INGRESO],Tabla5[MES],'RESUMEN 1'!M5,Tabla5[AÑO],'RESUMEN 1'!A5,Tabla5[TIPO DE PAGO],'RESUMEN 1'!B12) -> 0
A15: GASTOS | B15: EFECTIVO | C15: =SUMIFS(Tabla8[EGRESO],Tabla8[MES],'RESUMEN 1'!C5,Tabla8[AÑO],'RESUMEN 1'!A5,Tabla8[TIPO DE PAGO],'RESUMEN 1'!B15) -> 1758.15 | D15: =SUMIFS(Tabla8[EGRESO],Tabla8[MES],'RESUMEN 1'!D5,Tabla8[AÑO],'RESUMEN 1'!A5,Tabla8[TIPO DE PAGO],'RESUMEN 1'!B15) -> 1543.13 | L15: =SUMIFS(Tabla8[EGRESO],Tabla8[MES],'RESUMEN 1'!L5,Tabla8[AÑO],'RESUMEN 1'!A5,Tabla8[TIPO DE PAGO],'RESUMEN 1'!B15) -> 0 | M15: =SUMIFS(Tabla8[EGRESO],Tabla8[MES],'RESUMEN 1'!M5,Tabla8[AÑO],'RESUMEN 1'!A5,Tabla8[TIPO DE PAGO],'RESUMEN 1'!B15) -> 0
A16: GASTOS | B16: TARJETA | L16: =SUMIFS(Tabla8[EGRESO],Tabla8[MES],'RESUMEN 1'!L5,Tabla8[AÑO],'RESUMEN 1'!A5,Tabla8[TIPO DE PAGO],'RESUMEN 1'!B16) -> 0 | M16: =SUMIFS(Tabla8[EGRESO],Tabla8[MES],'RESUMEN 1'!M5,Tabla8[AÑO],'RESUMEN 1'!A5,Tabla8[TIPO DE PAGO],'RESUMEN 1'!B16) -> 0
A17: GASTOS | B17: JEP DANNA | C17: =SUMIFS(Tabla8[EGRESO],Tabla8[MES],'RESUMEN 1'!C5,Tabla8[AÑO],'RESUMEN 1'!A5,Tabla8[TIPO DE PAGO],'RESUMEN 1'!B17) -> 0 | L17: =SUMIFS(Tabla8[EGRESO],Tabla8[MES],'RESUMEN 1'!L5,Tabla8[AÑO],'RESUMEN 1'!A5,Tabla8[TIPO DE PAGO],'RESUMEN 1'!B17) -> 0 | M17: =SUMIFS(Tabla8[EGRESO],Tabla8[MES],'RESUMEN 1'!M5,Tabla8[AÑO],'RESUMEN 1'!A5,Tabla8[TIPO DE PAGO],'RESUMEN 1'!B17) -> 0
A18: GASTOS | B18: PICHINCHA | C18: =SUMIFS(Tabla8[EGRESO],Tabla8[MES],'RESUMEN 1'!C5,Tabla8[AÑO],'RESUMEN 1'!A5,Tabla8[TIPO DE PAGO],'RESUMEN 1'!B18) -> 2080.83 | L18: =SUMIFS(Tabla8[EGRESO],Tabla8[MES],'RESUMEN 1'!L5,Tabla8[AÑO],'RESUMEN 1'!A5,Tabla8[TIPO DE PAGO],'RESUMEN 1'!B18) -> 0 | M18: =SUMIFS(Tabla8[EGRESO],Tabla8[MES],'RESUMEN 1'!M5,Tabla8[AÑO],'RESUMEN 1'!A5,Tabla8[TIPO DE PAGO],'RESUMEN 1'!B18) -> 0
A19: GASTOS | B19: PRODUBANCO | L19: =SUMIFS(Tabla8[EGRESO],Tabla8[MES],'RESUMEN 1'!L5,Tabla8[AÑO],'RESUMEN 1'!A5,Tabla8[TIPO DE PAGO],'RESUMEN 1'!B19) -> 0 | M19: =SUMIFS(Tabla8[EGRESO],Tabla8[MES],'RESUMEN 1'!M5,Tabla8[AÑO],'RESUMEN 1'!A5,Tabla8[TIPO DE PAGO],'RESUMEN 1'!B19) -> 0
A20: GASTOS | B20: JARDIN AZUAYO | L20: =SUMIFS(Tabla8[EGRESO],Tabla8[MES],'RESUMEN 1'!L5,Tabla8[AÑO],'RESUMEN 1'!A5,Tabla8[TIPO DE PAGO],'RESUMEN 1'!B20) -> 0 | M20: =SUMIFS(Tabla8[EGRESO],Tabla8[MES],'RESUMEN 1'!M5,Tabla8[AÑO],'RESUMEN 1'!A5,Tabla8[TIPO DE PAGO],'RESUMEN 1'!B20) -> 0
A21: GASTOS | B21: JEP BRYAM | L21: =SUMIFS(Tabla8[EGRESO],Tabla8[MES],'RESUMEN 1'!L5,Tabla8[AÑO],'RESUMEN 1'!A5,Tabla8[TIPO DE PAGO],'RESUMEN 1'!B21) -> 0 | M21: =SUMIFS(Tabla8[EGRESO],Tabla8[MES],'RESUMEN 1'!M5,Tabla8[AÑO],'RESUMEN 1'!A5,Tabla8[TIPO DE PAGO],'RESUMEN 1'!B21) -> 0
A22: GASTOS | B22: BRYAM | C22: =SUMIFS(Tabla8[EGRESO],Tabla8[MES],'RESUMEN 1'!C5,Tabla8[AÑO],'RESUMEN 1'!A5,Tabla8[CUENTA],'RESUMEN 1'!B22) -> 55 | D22: =SUMIFS(Tabla8[EGRESO],Tabla8[MES],'RESUMEN 1'!D5,Tabla8[AÑO],'RESUMEN 1'!A5,Tabla8[CUENTA],'RESUMEN 1'!B22) -> 50 | L22: =SUMIFS(Tabla8[EGRESO],Tabla8[MES],'RESUMEN 1'!L6,Tabla8[AÑO],'RESUMEN 1'!A6,Tabla8[TIPO DE PAGO],'RESUMEN 1'!B22) -> 0 | M22: =SUMIFS(Tabla8[EGRESO],Tabla8[MES],'RESUMEN 1'!M6,Tabla8[AÑO],'RESUMEN 1'!A6,Tabla8[TIPO DE PAGO],'RESUMEN 1'!B22) -> 0
A23: GASTOS | B23: DANNA | C23: =SUMIFS(Tabla8[EGRESO],Tabla8[MES],'RESUMEN 1'!C5,Tabla8[AÑO],'RESUMEN 1'!A5,Tabla8[CUENTA],'RESUMEN 1'!B23) -> 181.34 | D23: =SUMIFS(Tabla8[EGRESO],Tabla8[MES],'RESUMEN 1'!D5,Tabla8[AÑO],'RESUMEN 1'!A5,Tabla8[CUENTA],'RESUMEN 1'!B23) -> 194.5 | L23: =SUMIFS(Tabla8[EGRESO],Tabla8[MES],'RESUMEN 1'!L7,Tabla8[AÑO],'RESUMEN 1'!A7,Tabla8[TIPO DE PAGO],'RESUMEN 1'!B23) -> 0 | M23: =SUMIFS(Tabla8[EGRESO],Tabla8[MES],'RESUMEN 1'!M7,Tabla8[AÑO],'RESUMEN 1'!A7,Tabla8[TIPO DE PAGO],'RESUMEN 1'!B23) -> 0
A26: POR PAGAR | B26: IMPORTLENTS | C26: =SUMIFS(Tabla6[TOTAL],Tabla6[MES],'RESUMEN 1'!C5,Tabla6[AÑO],'RESUMEN 1'!A5,Tabla6[DISTRIBUIDOR],'RESUMEN 1'!B26) -> 433.51 | D26: =SUMIFS(Tabla6[TOTAL],Tabla6[MES],'RESUMEN 1'!D5,Tabla6[AÑO],'RESUMEN 1'!A5,Tabla6[DISTRIBUIDOR],'RESUMEN 1'!B26) -> 212.59 | E26: =SUMIFS(Tabla6[TOTAL],Tabla6[MES],'RESUMEN 1'!E5,Tabla6[AÑO],'RESUMEN 1'!A5,Tabla6[DISTRIBUIDOR],'RESUMEN 1'!B26) -> 23.9 | F26: =SUMIFS(Tabla6[TOTAL],Tabla6[MES],'RESUMEN 1'!F5,Tabla6[AÑO],'RESUMEN 1'!A5,Tabla6[DISTRIBUIDOR],'RESUMEN 1'!B26) -> 0 | G26: =SUMIFS(Tabla6[TOTAL],Tabla6[MES],'RESUMEN 1'!G5,Tabla6[AÑO],'RESUMEN 1'!A5,Tabla6[DISTRIBUIDOR],'RESUMEN 1'!B26) -> 0 | H26: =SUMIFS(Tabla6[TOTAL],Tabla6[MES],'RESUMEN 1'!H5,Tabla6[AÑO],'RESUMEN 1'!A5,Tabla6[DISTRIBUIDOR],'RESUMEN 1'!B26) -> 0 | I26: =SUMIFS(Tabla6[TOTAL],Tabla6[MES],'RESUMEN 1'!I5,Tabla6[AÑO],'RESUMEN 1'!A5,Tabla6[DISTRIBUIDOR],'RESUMEN 1'!B26) -> 0 | J26: =SUMIFS(Tabla6[TOTAL],Tabla6[MES],'RESUMEN 1'!J5,Tabla6[AÑO],'RESUMEN 1'!A5,Tabla6[DISTRIBUIDOR],'RESUMEN 1'!B26) -> 0 | K26: =SUMIFS(Tabla6[TOTAL],Tabla6[MES],'RESUMEN 1'!K5,Tabla6[AÑO],'RESUMEN 1'!A5,Tabla6[DISTRIBUIDOR],'RESUMEN 1'!B26) -> 0 | L26: =SUMIFS(Tabla6[TOTAL],Tabla6[MES],'RESUMEN 1'!L5,Tabla6[AÑO],'RESUMEN 1'!A5,Tabla6[DISTRIBUIDOR],'RESUMEN 1'!B26) -> 0 | M26: =SUMIFS(Tabla6[TOTAL],Tabla6[MES],'RESUMEN 1'!M5,Tabla6[AÑO],'RESUMEN 1'!A5,Tabla6[DISTRIBUIDOR],'RESUMEN 1'!B26) -> 0 | N26: =SUMIFS(Tabla6[TOTAL],Tabla6[MES],'RESUMEN 1'!N5,Tabla6[AÑO],'RESUMEN 1'!A5,Tabla6[DISTRIBUIDOR],'RESUMEN 1'!B26) -> 0
A27: POR PAGAR | B27: OPTEC | C27: =SUMIFS(Tabla6[TOTAL],Tabla6[MES],'RESUMEN 1'!C5,Tabla6[AÑO],'RESUMEN 1'!A5,Tabla6[DISTRIBUIDOR],'RESUMEN 1'!B27) -> 480.59 | D27: =SUMIFS(Tabla6[TOTAL],Tabla6[MES],'RESUMEN 1'!D5,Tabla6[AÑO],'RESUMEN 1'!A5,Tabla6[DISTRIBUIDOR],'RESUMEN 1'!B27) -> 280.6 | E27: =SUMIFS(Tabla6[TOTAL],Tabla6[MES],'RESUMEN 1'!E5,Tabla6[AÑO],'RESUMEN 1'!A5,Tabla6[DISTRIBUIDOR],'RESUMEN 1'!B27) -> 0 | F27: =SUMIFS(Tabla6[TOTAL],Tabla6[MES],'RESUMEN 1'!F5,Tabla6[AÑO],'RESUMEN 1'!A5,Tabla6[DISTRIBUIDOR],'RESUMEN 1'!B27) -> 0 | G27: =SUMIFS(Tabla6[TOTAL],Tabla6[MES],'RESUMEN 1'!G5,Tabla6[AÑO],'RESUMEN 1'!A5,Tabla6[DISTRIBUIDOR],'RESUMEN 1'!B27) -> 0 | H27: =SUMIFS(Tabla6[TOTAL],Tabla6[MES],'RESUMEN 1'!H5,Tabla6[AÑO],'RESUMEN 1'!A5,Tabla6[DISTRIBUIDOR],'RESUMEN 1'!B27) -> 0 | I27: =SUMIFS(Tabla6[TOTAL],Tabla6[MES],'RESUMEN 1'!I5,Tabla6[AÑO],'RESUMEN 1'!A5,Tabla6[DISTRIBUIDOR],'RESUMEN 1'!B27) -> 0 | J27: =SUMIFS(Tabla6[TOTAL],Tabla6[MES],'RESUMEN 1'!J5,Tabla6[AÑO],'RESUMEN 1'!A5,Tabla6[DISTRIBUIDOR],'RESUMEN 1'!B27) -> 0 | K27: =SUMIFS(Tabla6[TOTAL],Tabla6[MES],'RESUMEN 1'!K5,Tabla6[AÑO],'RESUMEN 1'!A5,Tabla6[DISTRIBUIDOR],'RESUMEN 1'!B27) -> 0 | L27: =SUMIFS(Tabla6[TOTAL],Tabla6[MES],'RESUMEN 1'!L5,Tabla6[AÑO],'RESUMEN 1'!A5,Tabla6[DISTRIBUIDOR],'RESUMEN 1'!B27) -> 0 | M27: =SUMIFS(Tabla6[TOTAL],Tabla6[MES],'RESUMEN 1'!M5,Tabla6[AÑO],'RESUMEN 1'!A5,Tabla6[DISTRIBUIDOR],'RESUMEN 1'!B27) -> 0 | N27: =SUMIFS(Tabla6[TOTAL],Tabla6[MES],'RESUMEN 1'!N5,Tabla6[AÑO],'RESUMEN 1'!A5,Tabla6[DISTRIBUIDOR],'RESUMEN 1'!B27) -> 0
A28: POR PAGAR | B28: PECSA | C28: =SUMIFS(Tabla6[TOTAL],Tabla6[MES],'RESUMEN 1'!C5,Tabla6[AÑO],'RESUMEN 1'!A5,Tabla6[DISTRIBUIDOR],'RESUMEN 1'!B28) -> 302.44 | D28: =SUMIFS(Tabla6[TOTAL],Tabla6[MES],'RESUMEN 1'!D5,Tabla6[AÑO],'RESUMEN 1'!A5,Tabla6[DISTRIBUIDOR],'RESUMEN 1'!B28) -> 282.12 | E28: =SUMIFS(Tabla6[TOTAL],Tabla6[MES],'RESUMEN 1'!E5,Tabla6[AÑO],'RESUMEN 1'!A5,Tabla6[DISTRIBUIDOR],'RESUMEN 1'!B28) -> 0 | F28: =SUMIFS(Tabla6[TOTAL],Tabla6[MES],'RESUMEN 1'!F5,Tabla6[AÑO],'RESUMEN 1'!A5,Tabla6[DISTRIBUIDOR],'RESUMEN 1'!B28) -> 0 | G28: =SUMIFS(Tabla6[TOTAL],Tabla6[MES],'RESUMEN 1'!G5,Tabla6[AÑO],'RESUMEN 1'!A5,Tabla6[DISTRIBUIDOR],'RESUMEN 1'!B28) -> 0 | H28: =SUMIFS(Tabla6[TOTAL],Tabla6[MES],'RESUMEN 1'!H5,Tabla6[AÑO],'RESUMEN 1'!A5,Tabla6[DISTRIBUIDOR],'RESUMEN 1'!B28) -> 0 | I28: =SUMIFS(Tabla6[TOTAL],Tabla6[MES],'RESUMEN 1'!I5,Tabla6[AÑO],'RESUMEN 1'!A5,Tabla6[DISTRIBUIDOR],'RESUMEN 1'!B28) -> 0 | J28: =SUMIFS(Tabla6[TOTAL],Tabla6[MES],'RESUMEN 1'!J5,Tabla6[AÑO],'RESUMEN 1'!A5,Tabla6[DISTRIBUIDOR],'RESUMEN 1'!B28) -> 0 | K28: =SUMIFS(Tabla6[TOTAL],Tabla6[MES],'RESUMEN 1'!K5,Tabla6[AÑO],'RESUMEN 1'!A5,Tabla6[DISTRIBUIDOR],'RESUMEN 1'!B28) -> 0 | L28: =SUMIFS(Tabla6[TOTAL],Tabla6[MES],'RESUMEN 1'!L5,Tabla6[AÑO],'RESUMEN 1'!A5,Tabla6[DISTRIBUIDOR],'RESUMEN 1'!B28) -> 0 | M28: =SUMIFS(Tabla6[TOTAL],Tabla6[MES],'RESUMEN 1'!M5,Tabla6[AÑO],'RESUMEN 1'!A5,Tabla6[DISTRIBUIDOR],'RESUMEN 1'!B28) -> 0 | N28: =SUMIFS(Tabla6[TOTAL],Tabla6[MES],'RESUMEN 1'!N5,Tabla6[AÑO],'RESUMEN 1'!A5,Tabla6[DISTRIBUIDOR],'RESUMEN 1'!B28) -> 0
A29: POR PAGAR | B29: DANNA | C29: =SUMIFS(Tabla6[TOTAL],Tabla6[MES],'RESUMEN 1'!C5,Tabla6[AÑO],'RESUMEN 1'!A5,Tabla6[DISTRIBUIDOR],'RESUMEN 1'!B29) -> 0
A30: POR PAGAR | B30: BRYAM
A31: POR PAGAR | B31: DANNA
A32: POR PAGAR | B32: DANNA
B39: Saldo Mensual | C39: =+C6-C15 -> 4343.71 | D39: =+D6-D15 -> 676.87 | E39: =+E6-E15 -> 0 | F39: =+F6-F15 -> 0 | G39: =+G6-G15 -> 0 | H39: =+H6-H15 -> 0 | I39: =+I6-I15 -> 0 | J39: =+J6-J15 -> 0 | ... N39: =+N6-N15 -> 0
B41: Saldo Acumulado | C41: =+C39 -> 4343.71 | D41: =C41+D39 -> 5020.58 | E41: =D41+E39 -> 5020.58 | F41: =E41+F39 -> 5020.58 | G41: =F41+G39 -> 5020.58 | H41: =G41+H39 -> 5020.58 | I41: =H41+I39 -> 5020.58 | J41: =I41+J39 -> 5020.58 | K41: =J41+K39 -> 5020.58 | ... N41: =M41+N39 -> 5020.58

Sheet REPORTE CAJA
A1: RESUMEN DE MOVIMIENTOS
A2: FECHA | B2: NOMBRE | C2: APELLIDO | D2: PRODUCTO | E2: CANTIDAD | F2: PRECIO | G2: INGRESO | H2: DESCRIPCION | I2: OBSERVACION | J2: TIPO DE PAGO | K2: MES | L2: AÑO | M2: ORDEN | N2: SOFFI
A3: 45946 | B3: EDGAR | C3: PEÑAFIEL | D3: LENTES | E3: 1 | F3: 35 | G3: =E3*F3 -> 35 | H3: CANCELACION | J3: EFECTIVO | K3: =UPPER(TEXT(A3,"MMMM")) -> OCTUBRE | L3: =+YEAR(A3) -> 2025 | M3: 595 | N3: RV330
A4: 45946 | B4: MIGUEL | C4: MOROCHO | D4: LENTES | E4: 1 | F4: 45 | G4: =E4*F4 -> 45 | H4: CANCELACION | J4: EFECTIVO | K4: =UPPER(TEXT(A4,"MMMM")) -> OCTUBRE | L4: =+YEAR(A4) -> 2025 | M4: 596 | N4: RV331
A5: 45946 | B5: BELGICA | C5: GARCIA | D5: LENTES | E5: 1 | F5: 10 | G5: =E5*F5 -> 10 | H5: ABONO | J5: EFECTIVO | K5: =UPPER(TEXT(A5,"MMMM")) -> OCTUBRE | L5: =+YEAR(A5) -> 2025 | M5: 597 | N5: IT456
A6: 45946 | B6: DAN | C6: SAMANIEGO | D6: LENTES | E6: 1 | F6: 100 | G6: =E6*F6 -> 100 | H6: ABONO | J6: EFECTIVO | K6: =UPPER(TEXT(A6,"MMMM")) -> OCTUBRE | L6: =+YEAR(A6) -> 2025 | M6: 598 | N6: IT453
A7: 45946 | B7: MARCO | C7: MOCHA | D7: LENTES | E7: 1 | F7: 20 | G7: =E7*F7 -> 20 | H7: ABONO | J7: EFECTIVO | K7: =UPPER(TEXT(A7,"MMMM")) -> OCTUBRE | L7: =+YEAR(A7) -> 2025 | M7: 599 | N7: IT454
A8: 45946 | B8: BRYAN | C8: VIZHÑAY | D8: LENTES | E8: 1 | F8: 60 | G8: =E8*F8 -> 60 | H8: CANCELACION | J8: EFECTIVO | K8: =UPPER(TEXT(A8,"MMMM")) -> OCTUBRE | L8: =+YEAR(A8) -> 2025 | M8: 600 | N8: IT455
B9: 45946 | C9: COMPRAS | D9: OTROS | E9: 2 | F9: 1.5 | G9: =F9*E9 -> 3 | H9: FUNDAS DE BASURA FLOREADAS | J9: =UPPER(TEXT(B9,"MMMM")) -> OCTUBRE | K9: =+YEAR(B9) -> 2025 | L9: EFECTIVO | M9: ET606
B10: 45946 | C10: COMPRAS | D10: OTROS | E10: 1 | F10: 1 | G10: =F10*E10 -> 1 | H10: FUNDAS DE BASURA NEGRAS | J10: =UPPER(TEXT(B10,"MMMM")) -> OCTUBRE | K10: =+YEAR(B10) -> 2025 | L10: EFECTIVO | M10: ET606
B11: FECHA | C11: CUENTA | D11: DISTRIBUIDOR | E11: CANTIDAD | F11: PRECIO | G11: EGRESO | H11: DETALLE ADICIONAL | I11: NO. DOCUMENTO | J11: MES | K11: AÑO | L11: TIPO DE PAGO | M11: SOFFI
A12: 45946 | B12: ESTEBAN | C12: MATUTE | D12: CERTIFICADO | E12: 1 | F12: 5 | G12: =E12*F12 -> 5 | H12: CANCELACION | J12: EFECTIVO | K12: =UPPER(TEXT(A12,"MMMM")) -> OCTUBRE | L12: =+YEAR(A12) -> 2025 | N12: RV337
G13: =E13*F13 -> 0 | K13: =UPPER(TEXT(A13,"MMMM")) -> ENERO | L13: =+YEAR(A13) -> 1900
E16: INGRESOS | F16: =SUM(F3:F9) -> 271.5
E17: EGRESOS | F17: =SUM(G12:G13) -> 5 | H17: RECIBI CONFORME
H18: FECHA
D19: TOTAL ENTREGADO | F19: =F16-F17 -> 266.5
A21: RESUMEN DE MOVIMIENTOS
A22: FECHA | B22: NOMBRE | C22: APELLIDO | D22: PRODUCTO | E22: CANTIDAD | F22: PRECIO | G22: INGRESO | H22: DESCRIPCION | I22: OBSERVACION | J22: TIPO DE PAGO | K22: MES | L22: AÑO | M22: ORDEN | N22: SOFFI
A23: 45947 | B23: JOSE | C23: MAITE | D23: LENTES | E23: 1 | F23: 300 | G23: =E23*F23 -> 300 | H23: CANCELACION | J23: EFECTIVO | K23: =UPPER(TEXT(A23,"MMMM")) -> OCTUBRE | L23: =+YEAR(A23) -> 2025 | M23: 553
A24: 45947 | B24: HUGO | C24: CAJAMARCA | D24: LENTES | E24: 1 | F24: 185 | G24: =E24*F24 -> 185 | H24: CANCELACION | J24: EFECTIVO | K24: =UPPER(TEXT(A24,"MMMM")) -> OCTUBRE | L24: =+YEAR(A24) -> 2025 | M24: 594 | N24: FCE345
A25: 45947 | B25: BELGICA | C25: GARCIA | D25: LENTES | E25: 1 | F25: 35 | G25: =E25*F25 -> 35 | H25: CANCELACION | J25: EFECTIVO | K25: =UPPER(TEXT(A25,"MMMM")) -> OCTUBRE | L25: =+YEAR(A25) -> 2025 | M25: 597 | N25: RV339
A26: 45947 | B26: DAN | C26: SAMANIEGO | D26: LENTES | E26: 1 | F26: 20 | G26: =E26*F26 -> 20 | H26: CANCELACION | J26: EFECTIVO | K26: =UPPER(TEXT(A26,"MMMM")) -> OCTUBRE | L26: =+YEAR(A26) -> 2025 | M26: 598 | N26: RV338
A27: 45947 | B27: FABIAN | C27: MOSQUERA | D27: LENTES | E27: 1 | F27: 0 | G27: =E27*F27 -> 0 | H27: ABONO | J27: EFECTIVO | K27: =UPPER(TEXT(A27,"MMMM")) -> OCTUBRE | L27: =+YEAR(A27) -> 2025 | M27: 601
A28: 45947 | B28: HILDA LEONOR | C28: ANDRADE REYES | D28: LENTES | E28: 1 | F28: 5 | G28: =E28*F28 -> 5 | H28: ABONO | J28: EFECTIVO | K28: =UPPER(TEXT(A28,"MMMM")) -> OCTUBRE | L28: =+YEAR(A28) -> 2025 | M28: 602 | N28: IT458
B30: FECHA | C30: CUENTA | D30: DISTRIBUIDOR | E30: CANTIDAD | F30: PRECIO | G30: EGRESO | H30: DETALLE ADICIONAL | I30: NO. DOCUMENTO | J30: MES | K30: AÑO | L30: TIPO DE PAGO | M30: SOFFI
B31: 45947 | C31: COMPRAS | D31: OTROS | E31: 1 | F31: 0.5 | G31: =Tabla8[[#This Row],[CANTIDAD]]*Tabla8[[#This Row],[PRECIO]] -> 0.75 | H31: BRUJITA | J31: =UPPER(TEXT(B31,"MMMM")) -> OCTUBRE | K31: =+YEAR(B31) -> 2025 | L31: EFECTIVO | M31: ET607
B32: 45947 | C32: COMPRAS | D32: OTROS | E32: 1 | F32: 0.25 | G32: =Tabla8[[#This Row],[CANTIDAD]]*Tabla8[[#This Row],[PRECIO]] -> 40 | H32: LIMON | J32: =UPPER(TEXT(B32,"MMMM")) -> OCTUBRE | K32: =+YEAR(B32) -> 2025 | L32: EFECTIVO | M32: ET608
E34: INGRESO | F34: =SUM(F23:F28) -> 545
E35: EGRESO | F35: =SUM(F31:F32) -> 0.75
H36: RECIBI CONFORME
D37: TOTAL ENTREGADO | F37: =F34-F35 -> 544.25 | H37: FECHA
A40: RESUMEN DE MOVIMIENTOS
A41: FECHA | B41: NOMBRE | C41: APELLIDO | D41: PRODUCTO | E41: CANTIDAD | F41: PRECIO | G41: INGRESO | H41: DESCRIPCION | I41: OBSERVACION | J41: TIPO DE PAGO | K41: MES | L41: AÑO | M41: ORDEN | N41: SOFFI
A42: 45951 | B42: CARLOS | C42: LIMA | D42: LENTES | E42: 1 | F42: 130 | G42: =E42*F42 -> 130 | H42: CANCELACION | I42: RETIRA LENTES | J42: EFECTIVO | K42: =UPPER(TEXT(A42,"MMMM")) -> OCTUBRE | L42: =+YEAR(A42) -> 2025 | M42: 583
A43: 45948 | B43: MARCO | C43: MOCHA | D43: LENTES | E43: 1 | F43: 20 | G43: 20 | H43: CANCELACION | J43: EFECTIVO | K43: OCTUBRE | L43: 2025 | M43: 599
A44: 45950 | B44: JOSE | C44: ARPI | D44: LENTES | E44: 1 | F44: 150 | G44: 150 | H44: ABONO | J44: JEP BRYAM | K44: OCTUBRE | L44: 2025 | M44: 603 | N44: IT472
A45: 45950 | B45: FRANKLIN | C45: QUITUIZACA | D45: LENTES | E45: 1 | F45: 30 | G45: 30 | H45: ABONO | J45: EFECTIVO | K45: OCTUBRE | L45: 2025 | M45: 604 | N45: IT462
A46: 45950 | B46: MARTHA LUCIA | C46: ALVAREZ | D46: LENTES | E46: 1 | F46: 20 | G46: 20 | H46: ABONO | J46: EFECTIVO | K46: OCTUBRE | L46: 2025 | M46: 605 | N46: IT461
A47: 45950 | B47: JORGE LUIS | C47: LEON | D47: LENTES | E47: 1 | F47: 50 | G47: 50 | H47: ABONO | J47: EFECTIVO | K47: OCTUBRE | L47: 2025 | M47: 606 | N47: IT460
A48: 45950 | B48: JUAN | C48: PEÑA | F48: 0 | G48: 0 | K48: OCTUBRE | L48: 2025 | M48: 607
A49: 45950 | B49: JOSSELINE | C49: PEÑA | D49: ACCESORIOS | E49: 1 | F49: 5 | G49: 5 | H49: CANCELACION | I49: REPARACION | J49: EFECTIVO | K49: OCTUBRE | L49: 2025 | M49: 608 | N49: IT 459
A50: 45951 | B50: MARUJA | C50: HURTADO | G50: =E50*F50 -> 0 | K50: =UPPER(TEXT(A50,"MMMM")) -> OCTUBRE | L50: =+YEAR(A50) -> 2025 | M50: 609
A51: 45951 | B51: ANGEL | C51: SALAZAR | D51: LENTES | E51: 1 | F51: 60 | G51: =E51*F51 -> 60 | H51: ABONO | I51: ANTICIPO A LENTES | J51: EFECTIVO | K51: =UPPER(TEXT(A51,"MMMM")) -> OCTUBRE | L51: =+YEAR(A51) -> 2025 | M51: 610
A52: 45951 | B52: ANY | C52: DIAZ | D52: LENTES | E52: 1 | F52: 15 | G52: =E52*F52 -> 15 | H52: ABONO | I52: ANTICIPO A LENTES | J52: EFECTIVO | K52: =UPPER(TEXT(A52,"MMMM")) -> OCTUBRE | L52: =+YEAR(A52) -> 2025 | M52: 611 | N52: IT 470
A53: 45950 | B53: CAMBIO PLAQUETAS | D53: ACCESORIOS | E53: 1 | F53: 4 | G53: 4 | H53: CANCELACION | I53: REPARACION | J53: EFECTIVO | K53: OCTUBRE | L53: 2025 | M53: S/N
F54: INGRESO | G54: =SUM(G42:G53) -> 484
A59: FECHA | B59: CUENTA | C59: DISTRIBUIDOR | D59: CANTIDAD | E59: PRECIO | F59: EGRESO | G59: DETALLE ADICIONAL | H59: NO. DOCUMENTO | I59: MES | J59: AÑO | K59: TIPO DE PAGO | L59: Columna1
A60: 45948 | B60: COMPRAS | C60: OTROS | D60: 1 | E60: 15 | F60: =D60*E60 -> 15 | G60: ALIMENTACION SÀBADO | I60: =UPPER(TEXT(A60,"MMMM")) -> OCTUBRE | J60: =+YEAR(A60) -> 2025 | K60: EFECTIVO | L60: ET609
A61: 45948 | B61: COMPRAS | C61: OTROS | D61: 2 | E61: 0.2 | F61: =D61*E61 -> 0.4 | G61: PAN | I61: =UPPER(TEXT(A61,"MMMM")) -> OCTUBRE | J61: =+YEAR(A61) -> 2025 | K61: EFECTIVO | L61: ET609
A62: 45951 | B62: COMPRAS | C62: OTROS | D62: 1 | E62: 3 | F62: =D62*E62 -> 3 | G62: DESAYUNO | I62: =UPPER(TEXT(A62,"MMMM")) -> OCTUBRE | J62: =+YEAR(A62) -> 2025 | K62: EFECTIVO
A63: 45951 | B63: COMPRAS | C63: OTROS | D63: 1 | E63: 3.35 | F63: =D63*E63 -> 3.35 | G63: AGUA | I63: =UPPER(TEXT(A63,"MMMM")) -> OCTUBRE | J63: =+YEAR(A63) -> 2025 | K63: EFECTIVO
A64: 45951 | B64: COMPRAS | C64: OTROS | D64: 1 | E64: 20 | F64: =D64*E64 -> 20 | G64: ALMUERZO DB | I64: =UPPER(TEXT(A64,"MMMM")) -> OCTUBRE | J64: =+YEAR(A64) -> 2025 | K64: EFECTIVO
E65: EGRESO | F65: =SUM(F60:F64) -> 41.75
H66: RECIBI CONFORME
D67: TOTAL ENTREGADO | F67: =G54-F65 -> 442.25 | H67: FECHA
G69: DETALLE
F70: 20 | G70: 8 | H70: =F70*G70 -> 160
F71: 10 | G71: 8 | H71: =F71*G71 -> 80
F72: 5 | G72: 10 | H72: =F72*G72 -> 50
F73: 1 | G73: 1 | H73: =F73*G73 -> 1
F74: 0.25 | G74: 5 | H74: =F74*G74 -> 1.25
H76: =SUM(H70:H75) -> 292.25
A79: RESUMEN DE MOVIMIENTOS
A80: FECHA | B80: NOMBRE | C80: APELLIDO | D80: PRODUCTO | E80: CANTIDAD | F80: PRECIO | G80: INGRESO | H80: DESCRIPCION | I80: OBSERVACION | J80: TIPO DE PAGO | K80: MES | L80: AÑO | M80: ORDEN | N80: SOFFI
A81: 45954 | B81: SUSANA | C81: TEPAN | D81: LENTES | E81: 1 | F81: 60 | G81: =E81*F81 -> 60 | H81: CANCELACION | I81: ABONO FINAL A LENTES | J81: EFECTIVO | K81: =UPPER(TEXT(A81,"MMMM")) -> OCTUBRE | L81: =+YEAR(A81) -> 2025 | M81: 574 | N81: IT474
A82: 45953 | B82: FABIAN | C82: MOSQUERA | D82: LENTES | E82: 1 | F82: 5 | G82: =E82*F82 -> 5 | H82: CANCELACION | I82: TRASPASO | J82: EFECTIVO | K82: =UPPER(TEXT(A82,"MMMM")) -> OCTUBRE | L82: =+YEAR(A82) -> 2025 | M82: 601 | N82: RV345
A83: 45953 | B83: JOSE | C83: ARPI | D83: LENTES | E83: 1 | F83: 150 | G83: =E83*F83 -> 150 | H83: CANCELACION | J83: EFECTIVO | K83: =UPPER(TEXT(A83,"MMMM")) -> OCTUBRE | L83: =+YEAR(A83) -> 2025 | M83: 603 | N83: RV344
A84: 45953 | B84: MARTHA LUCIA | C84: ALVAREZ | D84: LENTES | E84: 1 | F84: 40 | G84: =E84*F84 -> 40 | H84: CANCELACION | J84: EFECTIVO | K84: =UPPER(TEXT(A84,"MMMM")) -> OCTUBRE | L84: =+YEAR(A84) -> 2025 | M84: 605 | N84: RV347
A85: 45952 | B85: MARUJA | C85: HURTADO | D85: ACCESORIOS | E85: 1 | F85: 12 | G85: =E85*F85 -> 12 | H85: CANCELACION | I85: VARILLAS | J85: EFECTIVO | K85: =UPPER(TEXT(A85,"MMMM")) -> OCTUBRE | L85: =+YEAR(A85) -> 2025 | M85: 609 | N85: RV342
A86: 45952 | B86: AMY | C86: DIAZ | D86: LENTES | E86: 1 | F86: 40 | G86: =E86*F86 -> 40 | H86: CANCELACION | J86: EFECTIVO | K86: =UPPER(TEXT(A86,"MMMM")) -> OCTUBRE | L86: =+YEAR(A86) -> 2025 | M86: 611 | N86: RV343
A87: 45951 | B87: DYLAN | C87: QUITO | D87: LENTES | E87: 1 | F87: 115 | G87: =E87*F87 -> 115 | H87: CANCELACION | I87: POLI BLANCO | J87: JEP BRYAM | K87: =UPPER(TEXT(A87,"MMMM")) -> OCTUBRE | L87: =+YEAR(A87) -> 2025 | M87: 612
A88: 45952 | B88: ROSARIO | C88: VILLACIS | D88: LENTES | E88: 1 | F88: 20 | G88: =E88*F88 -> 20 | H88: ABONO | J88: EFECTIVO | K88: =UPPER(TEXT(A88,"MMMM")) -> OCTUBRE | L88: =+YEAR(A88) -> 2025 | M88: 613
A89: 45953 | B89: MELANIE | C89: SALTO | D89: LENTES | E89: 1 | F89: 39 | G89: =E89*F89 -> 39 | H89: CANCELACION | I89: LENTES + PLAQUETAS | J89: EFECTIVO | K89: =UPPER(TEXT(A89,"MMMM")) -> OCTUBRE | L89: =+YEAR(A89) -> 2025 | M89: 614 | N89: RV346
A90: 45953 | B90: ANA | C90: AREVALO | D90: LENTES | E90: 1 | F90: 30 | G90: =E90*F90 -> 30 | H90: ABONO | J90: EFECTIVO | K90: =UPPER(TEXT(A90,"MMMM")) -> OCTUBRE | L90: =+YEAR(A90) -> 2025 | M90: 617 | N90: IT471
A91: 45953 | B91: JUAN | C91: UYAGUARI | D91: LENTES | E91: 1 | F91: 15 | G91: =E91*F91 -> 15 | H91: ABONO | J91: EFECTIVO | K91: =UPPER(TEXT(A91,"MMMM")) -> OCTUBRE | L91: =+YEAR(A91) -> 2025 | M91: 618 | N91: IT 473
A92: 45954 | B92: JUAN | C92: UYAGUARI | D92: LENTES | E92: 1 | F92: 70 | G92: =E92*F92 -> 70 | H92: CANCELACION | I92: LENTES | J92: EFECTIVO | K92: =UPPER(TEXT(A92,"MMMM")) -> OCTUBRE | L92: =+YEAR(A92) -> 2025 | M92: 618 | N92: RV349
A93: 45952 | B93: JAIME | C93: VELESACA | D93: LENTES | E93: 1 | F93: 100 | G93: =E93*F93 -> 100 | H93: ABONO | I93: PROGRESIVO | J93: EFECTIVO | K93: =UPPER(TEXT(A93,"MMMM")) -> OCTUBRE | L93: =+YEAR(A93) -> 2025 | M93: BRIGADA | N93: IT468
A94: 45952 | B94: DAYANNA | C94: MOROCHO | D94: LENTES | E94: 1 | F94: 20 | G94: =E94*F94 -> 20 | H94: ABONO | I94: L/C | J94: EFECTIVO | K94: =UPPER(TEXT(A94,"MMMM")) -> OCTUBRE | L94: =+YEAR(A94) -> 2025 | M94: S/N
A95: 45953 | B95: DAYANNA | C95: MOROCHO | D95: LENTES | E95: 1 | F95: 5 | G95: =E95*F95 -> 5 | H95: CANCELACION | I95: L/C | J95: EFECTIVO | K95: =UPPER(TEXT(A95,"MMMM")) -> OCTUBRE | L95: =+YEAR(A95) -> 2025 | M95: S/N
A96: 45953 | B96: CRISTINA | C96: AVILEZ | D96: CERTIFICADO | E96: 1 | F96: 5 | G96: =E96*F96 -> 5 | H96: CANCELACION | J96: EFECTIVO | K96: =UPPER(TEXT(A96,"MMMM")) -> OCTUBRE | L96: =+YEAR(A96) -> 2025 | M96: S/N | N96: RV348
A97: 45954 | B97: HILDA LEONOR | C97: ANDRADE | D97: LENTES | E97: 1 | F97: 10 | G97: =E97*F97 -> 10 | H97: ABONO | I97: LENTES | J97: EFECTIVO | K97: =UPPER(TEXT(A97,"MMMM")) -> OCTUBRE | L97: =+YEAR(A97) -> 2025 | N97: IT468
F98: INGRESO | G98: =SUM(G81:G97) -> 736
A100: FECHA | B100: CUENTA | C100: DISTRIBUIDOR | D100: CANTIDAD | E100: PRECIO | F100: EGRESO | G100: DETALLE ADICIONAL | H100: NO. DOCUMENTO | I100: MES | J100: AÑO | K100: TIPO DE PAGO | L100: SOFFI
A101: 45952 | B101: COMPRAS | C101: OTROS | D101: 1 | E101: 14 | F101: =D101*E101 -> 14 | G101: COMIDA CASA BD | I101: =UPPER(TEXT(A101,"MMMM")) -> OCTUBRE | J101: =+YEAR(A101) -> 2025 | K101: EFECTIVO | L101: ET614
A102: 45953 | B102: COMPRAS | C102: OTROS | D102: 1 | E102: 0.75 | F102: =D102*E102 -> 0.75 | G102: LIMON Y CINTA | I102: =UPPER(TEXT(A102,"MMMM")) -> OCTUBRE | J102: =+YEAR(A102) -> 2025 | K102: EFECTIVO | L102: ET615
A103: 45953 | B103: MOTORIZADO | C103: DELIVERY | D103: 1 | E103: 5 | F103: =D103*E103 -> 5 | I103: =UPPER(TEXT(A103,"MMMM")) -> OCTUBRE | J103: =+YEAR(A103) -> 2025 | K103: EFECTIVO | L103: ET615
A104: 45953 | C104: OTROS | D104: 1 | E104: 1.25 | F104: =D104*E104 -> 1.25 | G104: ELISABETH RUBIO | I104: =UPPER(TEXT(A104,"MMMM")) -> OCTUBRE | J104: =+YEAR(A104) -> 2025 | K104: EFECTIVO | L104: ET615
A105: 45954 | B105: COMIDA | C105: OTROS | D105: 1 | E105: 11 | F105: =D105*E105 -> 11 | G105: ELISABETH RUBIO | I105: =UPPER(TEXT(A105,"MMMM")) -> OCTUBRE | J105: =+YEAR(A105) -> 2025 | K105: EFECTIVO | L105: ET616
A106: 45954 | B106: COMIDA | C106: OTROS | D106: 1 | E106: 104 | F106: =D106*E106 -> 104 | G106: ALIMENTACION DEL 15/09/2025 AL 14/10/2025 | I106: =UPPER(TEXT(A106,"MMMM")) -> OCTUBRE | J106: =+YEAR(A106) -> 2025 | K106: EFECTIVO | L106: ET616
A107: 45954 | B107: BRYAM | C107: OTROS | D107: 1 | E107: 100 | F107: =D107*E107 -> 100 | G107: VIAJE | I107: =UPPER(TEXT(A107,"MMMM")) -> OCTUBRE | J107: =+YEAR(A107) -> 2025 | K107: EFECTIVO
E108: EGRESO | F108: =SUM(F100:F107) -> 236
E111: Total entregado | F111: =G98-F108 -> 500
A115: RESUMEN DE MOVIMIENTOS
A116: FECHA | B116: NOMBRE | C116: APELLIDO | D116: PRODUCTO | E116: CANTIDAD | F116: PRECIO | G116: INGRESO | H116: DESCRIPCION | I116: OBSERVACION | J116: TIPO DE PAGO | K116: MES | L116: AÑO | M116: ORDEN | N116: SOFFI
A117: 45957 | B117: FRANKLIN | C117: QUITUIZACA | D117: LENTES | E117: 1 | F117: 260 | G117: =E117*F117 -> 260 | H117: CANCELACION | I117: RETIRA LENTES | J117: EFECTIVO | K117: =UPPER(TEXT(A117,"MMMM")) -> OCTUBRE | L117: =+YEAR(A117) -> 2025 | M117: 604
A118: 45957 | B118: JORGE LUIS | C118: LEON | D118: LENTES | E118: 1 | F118: 70 | G118: =E118*F118 -> 70 | H118: CANCELACION | I118: RETIRA LENTES | J118: EFECTIVO | K118: =UPPER(TEXT(A118,"MMMM")) -> OCTUBRE | L118: =+YEAR(A118) -> 2025 | M118: 606
A119: 45957 | B119: RAUL | C119: BERMEO | M119: 615 | N119: NADA
A120: 45955 | B120: TANNYA | C120: AUQUILLA | D120: LENTES | E120: 1 | F120: 35 | H120: CANCELACION | I120: PAGO CON DE UNA | J120: PICHINCHA | K120: =UPPER(TEXT(A120,"MMMM")) -> OCTUBRE | L120: =+YEAR(A120) -> 2025 | M120: 616 | N120: RV350
A121: 45955 | B121: ANA | C121: AREVALO | D121: LENTES | E121: 1 | F121: 65 | G121: 35 | H121: CANCELACION | I121: LENTES | J121: EFECTIVO | K121: =UPPER(TEXT(A121,"MMMM")) -> OCTUBRE | L121: =+YEAR(A121) -> 2025 | M121: 617 | N121: FCE348
...

Sheet RESUMEN 2

Sheet TABLA
A10: Etiquetas de fila
A11: LENTES
A12: CERTIFICADO
A13: Total general

Sheet Hoja1

Sheet CUENTAS CONTABLES
A4: CUENTAS DE INGRESO | C4: CUENTAS DE GASTO | E4: PRODUCTO | G4: TIPO DE PAGO | I4: DISTRIBUIDOR | K4: ESTADO
A5: ABONO | C5: BISEL Y LUNAS | E5: LENTES | G5: EFECTIVO | I5: ALEPSA | K5: POR PAGAR
A6: CANCELACION | C6: MOTORIZADO | E6: CERTIFICADO | G6: TARJETA | I6: IMPORTLENTS | K6: PAGADO
C7: COMIDA | E7: CARRERAS | G7: JEP DANNA | I7: DELIVERY
C8: DEPOSITO | E8: ALIMENTACION | G8: PICHINCHA | I8: PERSONAL
C9: LUZ | E9: DISTRIBUIDORA | G9: PRODUBANCO | I9: OPTICA
C10: AGUA | E10: ACCESORIOS | G10: JARDIN AZUAYO | I10: JEP
C11: COMPRAS | G11: JEP BRYAM | I11: PICHINCHA
C12: ARRIENDO | G12: BRYAM | I12: PRODUBANCO
C13: DEPOSITO | G13: DE UNA | I13: JARDIN AZUAYO
C14: BRYAM | G14: DANNA | I14: OTROS
C15: DANNA | I15: OPTEC
C16: OTROS | I16: PECSA
I17: PROVISION LENS
I18: BRYAM
I19: DANNA
I20: DELBAK
I21: PROVISION CUENCA
I22: TECNILENTS
I23: ANDINA
I24: GUARTAZACA
I25: RESTREPO
